<?xml version="1.0" encoding="utf-8"?>
<FEDRecords>
    <FED Num="0">
        <FeatureCtIdx>1410</FeatureCtIdx>
        <OffsetX>3179.473</OffsetX>
        <OffsetY>-7731.854</OffsetY>
        <OffsetZ>0.000</OffsetZ>
        <Heading>180.0</Heading>
    </FED>
    <FED Num="1">
        <FeatureCtIdx>1870</FeatureCtIdx>
        <Value>90</Value>
        <OffsetX>3179.478</OffsetX>
        <OffsetY>-7821.820</OffsetY>
        <OffsetZ>0.000</OffsetZ>
        <Heading>0.0</Heading>
    </FED>
    <FED Num="2">
        <FeatureCtIdx>1413</FeatureCtIdx>
        <Value>95</Value>
        <OffsetX>3179.453</OffsetX>
        <OffsetY>-6393.308</OffsetY>
        <OffsetZ>0.000</OffsetZ>
        <Heading>180.0</Heading>
    </FED>
    <FED Num="3">
        <FeatureCtIdx>1412</FeatureCtIdx>
        <Value>95</Value>
        <OffsetX>3179.439</OffsetX>
        <OffsetY>-3609.824</OffsetY>
        <OffsetZ>0.000</OffsetZ>
        <Heading>180.0</Heading>
    </FED>
    <FED Num="4">
        <FeatureCtIdx>972</FeatureCtIdx>
        <Value>95</Value>
        <OffsetX>3179.466</OffsetX>
        <OffsetY>-841.319</OffsetY>
        <OffsetZ>0.000</OffsetZ>
        <Heading>180.0</Heading>
    </FED>
    <FED Num="5">
        <FeatureCtIdx>1870</FeatureCtIdx>
        <Value>90</Value>
        <OffsetX>3179.495</OffsetX>
        <OffsetY>572.200</OffsetY>
        <OffsetZ>0.000</OffsetZ>
        <Heading>180.0</Heading>
    </FED>
    <FED Num="6">
        <FeatureCtIdx>1410</FeatureCtIdx>
        <OffsetX>3179.508</OffsetX>
        <OffsetY>482.186</OffsetY>
        <OffsetZ>0.000</OffsetZ>
        <Heading>0.0</Heading>
    </FED>
    <FED Num="7">
        <FeatureCtIdx>1414</FeatureCtIdx>
        <OffsetX>4684.280</OffsetX>
        <OffsetY>-3624.817</OffsetY>
        <OffsetZ>0.000</OffsetZ>
        <Heading>180.0</Heading>
    </FED>
    <FED Num="8">
        <FeatureCtIdx>1917</FeatureCtIdx>
        <OffsetX>4686.879</OffsetX>
        <OffsetY>-3628.058</OffsetY>
        <OffsetZ>0.000</OffsetZ>
        <Heading>180.0</Heading>
    </FED>
    <FED Num="9">
        <FeatureCtIdx>627</FeatureCtIdx>
        <Value>80</Value>
        <OffsetX>3793.890</OffsetX>
        <OffsetY>-4729.016</OffsetY>
        <OffsetZ>0.000</OffsetZ>
        <Heading>0.0</Heading>
    </FED>
    <FED Num="10">
        <FeatureCtIdx>1868</FeatureCtIdx>
        <OffsetX>3179.601</OffsetX>
        <OffsetY>-7982.403</OffsetY>
        <OffsetZ>0.000</OffsetZ>
        <Heading>180.0</Heading>
    </FED>
    <FED Num="11">
        <FeatureCtIdx>1868</FeatureCtIdx>
        <OffsetX>3179.601</OffsetX>
        <OffsetY>732.600</OffsetY>
        <OffsetZ>0.000</OffsetZ>
        <Heading>0.0</Heading>
    </FED>
    <FED Num="12">
        <FeatureCtIdx>1007</FeatureCtIdx>
        <OffsetX>3005.845</OffsetX>
        <OffsetY>-6759.050</OffsetY>
        <OffsetZ>0.000</OffsetZ>
        <Heading>180.0</Heading>
    </FED>
    <FED Num="13">
        <FeatureCtIdx>1007</FeatureCtIdx>
        <OffsetX>3335.450</OffsetX>
        <OffsetY>-472.776</OffsetY>
        <OffsetZ>0.000</OffsetZ>
        <Heading>0.0</Heading>
    </FED>
    <FED Num="14">
        <FeatureCtIdx>1963</FeatureCtIdx>
        <OffsetX>3278.561</OffsetX>
        <OffsetY>-4940.734</OffsetY>
        <OffsetZ>0.000</OffsetZ>
        <Heading>0.0</Heading>
    </FED>
    <FED Num="15">
        <FeatureCtIdx>4047</FeatureCtIdx>
        <OffsetX>3278.671</OffsetX>
        <OffsetY>294.126</OffsetY>
        <OffsetZ>0.000</OffsetZ>
        <Heading>0.0</Heading>
    </FED>
    <FED Num="16">
        <FeatureCtIdx>4065</FeatureCtIdx>
        <OffsetX>3278.774</OffsetX>
        <OffsetY>-7551.657</OffsetY>
        <OffsetZ>0.000</OffsetZ>
        <Heading>0.0</Heading>
    </FED>
    <FED Num="17">
        <FeatureCtIdx>1547</FeatureCtIdx>
        <OffsetX>4549.093</OffsetX>
        <OffsetY>-1782.016</OffsetY>
        <OffsetZ>0.000</OffsetZ>
        <Heading>90.0</Heading>
    </FED>
    <FED Num="18">
        <FeatureCtIdx>1547</FeatureCtIdx>
        <OffsetX>3278.414</OffsetX>
        <OffsetY>289.811</OffsetY>
        <OffsetZ>0.000</OffsetZ>
        <Heading>180.0</Heading>
    </FED>
    <FED Num="19">
        <FeatureCtIdx>1547</FeatureCtIdx>
        <OffsetX>4549.113</OffsetX>
        <OffsetY>-3906.899</OffsetY>
        <OffsetZ>0.000</OffsetZ>
        <Heading>90.0</Heading>
    </FED>
    <FED Num="20">
        <FeatureCtIdx>1547</FeatureCtIdx>
        <OffsetX>3722.082</OffsetX>
        <OffsetY>247.208</OffsetY>
        <OffsetZ>0.000</OffsetZ>
        <Heading>67.0</Heading>
    </FED>
    <FED Num="21">
        <FeatureCtIdx>1546</FeatureCtIdx>
        <OffsetX>3278.562</OffsetX>
        <OffsetY>-4933.732</OffsetY>
        <OffsetZ>0.000</OffsetZ>
        <Heading>0.0</Heading>
    </FED>
    <FED Num="22">
        <FeatureCtIdx>1546</FeatureCtIdx>
        <OffsetX>3935.140</OffsetX>
        <OffsetY>-4938.440</OffsetY>
        <OffsetZ>0.000</OffsetZ>
        <Heading>0.0</Heading>
    </FED>
    <FED Num="23">
        <FeatureCtIdx>1546</FeatureCtIdx>
        <OffsetX>3934.778</OffsetX>
        <OffsetY>-5123.507</OffsetY>
        <OffsetZ>0.000</OffsetZ>
        <Heading>0.0</Heading>
    </FED>
    <FED Num="24">
        <FeatureCtIdx>1545</FeatureCtIdx>
        <OffsetX>3279.024</OffsetX>
        <OffsetY>-7547.297</OffsetY>
        <OffsetZ>0.000</OffsetZ>
        <Heading>0.0</Heading>
    </FED>
    <FED Num="25">
        <FeatureCtIdx>1545</FeatureCtIdx>
        <OffsetX>3968.944</OffsetX>
        <OffsetY>-5156.544</OffsetY>
        <OffsetZ>0.000</OffsetZ>
        <Heading>270.0</Heading>
    </FED>
    <FED Num="26">
        <FeatureCtIdx>1545</FeatureCtIdx>
        <OffsetX>4152.914</OffsetX>
        <OffsetY>-5156.389</OffsetY>
        <OffsetZ>0.000</OffsetZ>
        <Heading>270.0</Heading>
    </FED>
    <FED Num="27">
        <FeatureCtIdx>850</FeatureCtIdx>
        <OffsetX>3054.982</OffsetX>
        <OffsetY>-6976.918</OffsetY>
        <OffsetZ>0.000</OffsetZ>
        <Heading>270.0</Heading>
    </FED>
    <FED Num="28">
        <FeatureCtIdx>850</FeatureCtIdx>
        <OffsetX>3305.004</OffsetX>
        <OffsetY>-6976.920</OffsetY>
        <OffsetZ>0.000</OffsetZ>
        <Heading>270.0</Heading>
    </FED>
    <FED Num="29">
        <FeatureCtIdx>850</FeatureCtIdx>
        <OffsetX>3305.125</OffsetX>
        <OffsetY>-272.484</OffsetY>
        <OffsetZ>0.000</OffsetZ>
        <Heading>90.0</Heading>
    </FED>
    <FED Num="30">
        <FeatureCtIdx>850</FeatureCtIdx>
        <OffsetX>3055.110</OffsetX>
        <OffsetY>-272.478</OffsetY>
        <OffsetZ>0.000</OffsetZ>
        <Heading>90.0</Heading>
    </FED>
    <FED Num="31">
        <FeatureCtIdx>851</FeatureCtIdx>
        <OffsetX>3054.978</OffsetX>
        <OffsetY>-5976.920</OffsetY>
        <OffsetZ>0.000</OffsetZ>
        <Heading>270.0</Heading>
    </FED>
    <FED Num="32">
        <FeatureCtIdx>851</FeatureCtIdx>
        <OffsetX>3305.004</OffsetX>
        <OffsetY>-5976.921</OffsetY>
        <OffsetZ>0.000</OffsetZ>
        <Heading>270.0</Heading>
    </FED>
    <FED Num="33">
        <FeatureCtIdx>851</FeatureCtIdx>
        <OffsetX>3055.109</OffsetX>
        <OffsetY>-1272.484</OffsetY>
        <OffsetZ>0.000</OffsetZ>
        <Heading>90.0</Heading>
    </FED>
    <FED Num="34">
        <FeatureCtIdx>851</FeatureCtIdx>
        <OffsetX>3305.127</OffsetX>
        <OffsetY>-1272.483</OffsetY>
        <OffsetZ>0.000</OffsetZ>
        <Heading>90.0</Heading>
    </FED>
    <FED Num="35">
        <FeatureCtIdx>1779</FeatureCtIdx>
        <OffsetX>3055.110</OffsetX>
        <OffsetY>-2272.488</OffsetY>
        <OffsetZ>0.000</OffsetZ>
        <Heading>90.0</Heading>
    </FED>
    <FED Num="36">
        <FeatureCtIdx>1779</FeatureCtIdx>
        <OffsetX>3305.025</OffsetX>
        <OffsetY>-2272.489</OffsetY>
        <OffsetZ>0.000</OffsetZ>
        <Heading>90.0</Heading>
    </FED>
    <FED Num="37">
        <FeatureCtIdx>1779</FeatureCtIdx>
        <OffsetX>3055.081</OffsetX>
        <OffsetY>-4976.919</OffsetY>
        <OffsetZ>0.000</OffsetZ>
        <Heading>270.0</Heading>
    </FED>
    <FED Num="38">
        <FeatureCtIdx>1019</FeatureCtIdx>
        <Value>60</Value>
        <OffsetX>4292.707</OffsetX>
        <OffsetY>-2842.605</OffsetY>
        <OffsetZ>0.000</OffsetZ>
        <Heading>90.0</Heading>
    </FED>
    <FED Num="39">
        <FeatureCtIdx>1019</FeatureCtIdx>
        <Value>60</Value>
        <OffsetX>4293.020</OffsetX>
        <OffsetY>-3138.332</OffsetY>
        <OffsetZ>0.000</OffsetZ>
        <Heading>90.0</Heading>
    </FED>
    <FED Num="40">
        <FeatureCtIdx>1019</FeatureCtIdx>
        <Value>60</Value>
        <OffsetX>4292.816</OffsetX>
        <OffsetY>-3434.937</OffsetY>
        <OffsetZ>0.000</OffsetZ>
        <Heading>90.0</Heading>
    </FED>
    <FED Num="41">
        <FeatureCtIdx>1025</FeatureCtIdx>
        <OffsetX>3698.839</OffsetX>
        <OffsetY>-3953.928</OffsetY>
        <OffsetZ>0.000</OffsetZ>
        <Heading>0.0</Heading>
    </FED>
    <FED Num="42">
        <FeatureCtIdx>1025</FeatureCtIdx>
        <OffsetX>4785.038</OffsetX>
        <OffsetY>-4363.523</OffsetY>
        <OffsetZ>0.000</OffsetZ>
        <Heading>0.0</Heading>
    </FED>
    <FED Num="43">
        <FeatureCtIdx>1025</FeatureCtIdx>
        <OffsetX>5061.836</OffsetX>
        <OffsetY>-3456.921</OffsetY>
        <OffsetZ>0.000</OffsetZ>
        <Heading>180.0</Heading>
    </FED>
    <FED Num="44">
        <FeatureCtIdx>1025</FeatureCtIdx>
        <OffsetX>5209.509</OffsetX>
        <OffsetY>-4465.383</OffsetY>
        <OffsetZ>0.000</OffsetZ>
        <Heading>0.0</Heading>
    </FED>
    <FED Num="45">
        <FeatureCtIdx>1025</FeatureCtIdx>
        <OffsetX>4946.175</OffsetX>
        <OffsetY>-6499.662</OffsetY>
        <OffsetZ>0.000</OffsetZ>
        <Heading>90.0</Heading>
    </FED>
    <FED Num="46">
        <FeatureCtIdx>1025</FeatureCtIdx>
        <OffsetX>5124.760</OffsetX>
        <OffsetY>-6320.778</OffsetY>
        <OffsetZ>0.000</OffsetZ>
        <Heading>180.0</Heading>
    </FED>
    <FED Num="47">
        <FeatureCtIdx>1025</FeatureCtIdx>
        <OffsetX>5125.166</OffsetX>
        <OffsetY>-6678.302</OffsetY>
        <OffsetZ>0.000</OffsetZ>
        <Heading>0.0</Heading>
    </FED>
    <FED Num="48">
        <FeatureCtIdx>1025</FeatureCtIdx>
        <OffsetX>5303.751</OffsetX>
        <OffsetY>-6499.417</OffsetY>
        <OffsetZ>0.000</OffsetZ>
        <Heading>270.0</Heading>
    </FED>
    <FED Num="49">
        <FeatureCtIdx>1025</FeatureCtIdx>
        <OffsetX>6264.250</OffsetX>
        <OffsetY>-3377.783</OffsetY>
        <OffsetZ>0.000</OffsetZ>
        <Heading>0.0</Heading>
    </FED>
    <FED Num="50">
        <FeatureCtIdx>1025</FeatureCtIdx>
        <OffsetX>6242.417</OffsetX>
        <OffsetY>-4589.748</OffsetY>
        <OffsetZ>0.000</OffsetZ>
        <Heading>180.0</Heading>
    </FED>
    <FED Num="51">
        <FeatureCtIdx>1025</FeatureCtIdx>
        <OffsetX>6442.896</OffsetX>
        <OffsetY>-3735.684</OffsetY>
        <OffsetZ>0.000</OffsetZ>
        <Heading>90.0</Heading>
    </FED>
    <FED Num="52">
        <FeatureCtIdx>1025</FeatureCtIdx>
        <OffsetX>6421.118</OffsetX>
        <OffsetY>-4411.302</OffsetY>
        <OffsetZ>0.000</OffsetZ>
        <Heading>90.0</Heading>
    </FED>
    <FED Num="53">
        <FeatureCtIdx>103</FeatureCtIdx>
        <Value>20</Value>
        <OffsetX>4769.270</OffsetX>
        <OffsetY>-4281.225</OffsetY>
        <OffsetZ>0.000</OffsetZ>
        <Heading>90.0</Heading>
    </FED>
    <FED Num="54">
        <FeatureCtIdx>112</FeatureCtIdx>
        <Value>50</Value>
        <OffsetX>4450.665</OffsetX>
        <OffsetY>143.088</OffsetY>
        <OffsetZ>0.000</OffsetZ>
        <Heading>10.0</Heading>
    </FED>
    <FED Num="55">
        <FeatureCtIdx>112</FeatureCtIdx>
        <Value>50</Value>
        <OffsetX>4532.009</OffsetX>
        <OffsetY>-39.621</OffsetY>
        <OffsetZ>0.000</OffsetZ>
        <Heading>10.0</Heading>
    </FED>
    <FED Num="56">
        <FeatureCtIdx>112</FeatureCtIdx>
        <Value>50</Value>
        <OffsetX>4578.560</OffsetX>
        <OffsetY>200.031</OffsetY>
        <OffsetZ>0.000</OffsetZ>
        <Heading>10.0</Heading>
    </FED>
    <FED Num="57">
        <FeatureCtIdx>112</FeatureCtIdx>
        <Value>50</Value>
        <OffsetX>4613.357</OffsetX>
        <OffsetY>-222.324</OffsetY>
        <OffsetZ>0.000</OffsetZ>
        <Heading>10.0</Heading>
    </FED>
    <FED Num="58">
        <FeatureCtIdx>112</FeatureCtIdx>
        <Value>50</Value>
        <OffsetX>4659.906</OffsetX>
        <OffsetY>17.321</OffsetY>
        <OffsetZ>0.000</OffsetZ>
        <Heading>10.0</Heading>
    </FED>
    <FED Num="59">
        <FeatureCtIdx>112</FeatureCtIdx>
        <Value>50</Value>
        <OffsetX>4741.252</OffsetX>
        <OffsetY>-165.391</OffsetY>
        <OffsetZ>0.000</OffsetZ>
        <Heading>10.0</Heading>
    </FED>
    <FED Num="60">
        <FeatureCtIdx>1232</FeatureCtIdx>
        <OffsetX>3029.715</OffsetX>
        <OffsetY>-6392.417</OffsetY>
        <OffsetZ>0.000</OffsetZ>
        <Heading>270.0</Heading>
    </FED>
    <FED Num="61">
        <FeatureCtIdx>1232</FeatureCtIdx>
        <OffsetX>3329.719</OffsetX>
        <OffsetY>-6392.420</OffsetY>
        <OffsetZ>0.000</OffsetZ>
        <Heading>270.0</Heading>
    </FED>
    <FED Num="62">
        <FeatureCtIdx>1232</FeatureCtIdx>
        <OffsetX>3029.622</OffsetX>
        <OffsetY>-857.422</OffsetY>
        <OffsetZ>0.000</OffsetZ>
        <Heading>90.0</Heading>
    </FED>
    <FED Num="63">
        <FeatureCtIdx>1232</FeatureCtIdx>
        <OffsetX>3329.620</OffsetX>
        <OffsetY>-857.423</OffsetY>
        <OffsetZ>0.000</OffsetZ>
        <Heading>90.0</Heading>
    </FED>
    <FED Num="64">
        <FeatureCtIdx>1325</FeatureCtIdx>
        <OffsetX>2486.448</OffsetX>
        <OffsetY>-456.098</OffsetY>
        <OffsetZ>0.000</OffsetZ>
        <Heading>0.0</Heading>
    </FED>
    <FED Num="65">
        <FeatureCtIdx>1325</FeatureCtIdx>
        <OffsetX>2474.197</OffsetX>
        <OffsetY>130.951</OffsetY>
        <OffsetZ>0.000</OffsetZ>
        <Heading>0.0</Heading>
    </FED>
    <FED Num="66">
        <FeatureCtIdx>1346</FeatureCtIdx>
        <Value>75</Value>
        <OffsetX>3786.198</OffsetX>
        <OffsetY>-4175.063</OffsetY>
        <OffsetZ>0.000</OffsetZ>
        <Heading>0.0</Heading>
    </FED>
    <FED Num="67">
        <FeatureCtIdx>150</FeatureCtIdx>
        <Value>70</Value>
        <OffsetX>3771.328</OffsetX>
        <OffsetY>-4292.425</OffsetY>
        <OffsetZ>0.000</OffsetZ>
        <Heading>180.0</Heading>
    </FED>
    <FED Num="68">
        <FeatureCtIdx>152</FeatureCtIdx>
        <Value>50</Value>
        <OffsetX>4661.424</OffsetX>
        <OffsetY>-1735.569</OffsetY>
        <OffsetZ>0.000</OffsetZ>
        <Heading>270.0</Heading>
    </FED>
    <FED Num="69">
        <FeatureCtIdx>152</FeatureCtIdx>
        <Value>50</Value>
        <OffsetX>4765.386</OffsetX>
        <OffsetY>-1735.303</OffsetY>
        <OffsetZ>0.000</OffsetZ>
        <Heading>270.0</Heading>
    </FED>
    <FED Num="70">
        <FeatureCtIdx>152</FeatureCtIdx>
        <Value>50</Value>
        <OffsetX>5001.413</OffsetX>
        <OffsetY>-4213.763</OffsetY>
        <OffsetZ>0.000</OffsetZ>
        <Heading>180.0</Heading>
    </FED>
    <FED Num="71">
        <FeatureCtIdx>152</FeatureCtIdx>
        <Value>50</Value>
        <OffsetX>5001.680</OffsetX>
        <OffsetY>-4317.729</OffsetY>
        <OffsetZ>0.000</OffsetZ>
        <Heading>180.0</Heading>
    </FED>
    <FED Num="72">
        <FeatureCtIdx>1871</FeatureCtIdx>
        <OffsetX>3782.434</OffsetX>
        <OffsetY>-4431.638</OffsetY>
        <OffsetZ>0.000</OffsetZ>
        <Heading>315.0</Heading>
    </FED>
    <FED Num="73">
        <FeatureCtIdx>1912</FeatureCtIdx>
        <Value>30</Value>
        <OffsetX>4933.721</OffsetX>
        <OffsetY>-3765.751</OffsetY>
        <OffsetZ>0.000</OffsetZ>
        <Heading>180.0</Heading>
    </FED>
    <FED Num="74">
        <FeatureCtIdx>2020</FeatureCtIdx>
        <Value>75</Value>
        <OffsetX>5208.938</OffsetX>
        <OffsetY>-6505.759</OffsetY>
        <OffsetZ>0.000</OffsetZ>
        <Heading>315.0</Heading>
    </FED>
    <FED Num="75">
        <FeatureCtIdx>2038</FeatureCtIdx>
        <OffsetX>4352.494</OffsetX>
        <OffsetY>-476.810</OffsetY>
        <OffsetZ>0.000</OffsetZ>
        <Heading>245.0</Heading>
    </FED>
    <FED Num="76">
        <FeatureCtIdx>2038</FeatureCtIdx>
        <OffsetX>3945.630</OffsetX>
        <OffsetY>-3878.183</OffsetY>
        <OffsetZ>0.000</OffsetZ>
        <Heading>229.0</Heading>
    </FED>
    <FED Num="77">
        <FeatureCtIdx>2038</FeatureCtIdx>
        <OffsetX>4303.143</OffsetX>
        <OffsetY>-3309.285</OffsetY>
        <OffsetZ>0.000</OffsetZ>
        <Heading>92.0</Heading>
    </FED>
    <FED Num="78">
        <FeatureCtIdx>2038</FeatureCtIdx>
        <OffsetX>4619.028</OffsetX>
        <OffsetY>-1781.657</OffsetY>
        <OffsetZ>0.000</OffsetZ>
        <Heading>176.0</Heading>
    </FED>
    <FED Num="79">
        <FeatureCtIdx>2038</FeatureCtIdx>
        <OffsetX>4208.357</OffsetX>
        <OffsetY>-5420.985</OffsetY>
        <OffsetZ>0.000</OffsetZ>
        <Heading>229.0</Heading>
    </FED>
    <FED Num="80">
        <FeatureCtIdx>2038</FeatureCtIdx>
        <OffsetX>4491.406</OffsetX>
        <OffsetY>-5106.583</OffsetY>
        <OffsetZ>0.000</OffsetZ>
        <Heading>270.0</Heading>
    </FED>
    <FED Num="81">
        <FeatureCtIdx>2038</FeatureCtIdx>
        <OffsetX>5024.223</OffsetX>
        <OffsetY>-4168.579</OffsetY>
        <OffsetZ>0.000</OffsetZ>
        <Heading>91.0</Heading>
    </FED>
    <FED Num="82">
        <FeatureCtIdx>2038</FeatureCtIdx>
        <OffsetX>5189.032</OffsetX>
        <OffsetY>-3670.421</OffsetY>
        <OffsetZ>0.000</OffsetZ>
        <Heading>177.0</Heading>
    </FED>
    <FED Num="83">
        <FeatureCtIdx>2038</FeatureCtIdx>
        <OffsetX>5998.018</OffsetX>
        <OffsetY>-4344.486</OffsetY>
        <OffsetZ>0.000</OffsetZ>
        <Heading>4.0</Heading>
    </FED>
    <FED Num="84">
        <FeatureCtIdx>2039</FeatureCtIdx>
        <OffsetX>4334.716</OffsetX>
        <OffsetY>-2725.462</OffsetY>
        <OffsetZ>0.000</OffsetZ>
        <Heading>89.0</Heading>
    </FED>
    <FED Num="85">
        <FeatureCtIdx>2039</FeatureCtIdx>
        <OffsetX>3869.866</OffsetX>
        <OffsetY>-5534.962</OffsetY>
        <OffsetZ>0.000</OffsetZ>
        <Heading>129.0</Heading>
    </FED>
    <FED Num="86">
        <FeatureCtIdx>2039</FeatureCtIdx>
        <OffsetX>4190.494</OffsetX>
        <OffsetY>-3904.628</OffsetY>
        <OffsetZ>0.000</OffsetZ>
        <Heading>99.0</Heading>
    </FED>
    <FED Num="87">
        <FeatureCtIdx>2039</FeatureCtIdx>
        <OffsetX>4741.298</OffsetX>
        <OffsetY>-1823.449</OffsetY>
        <OffsetZ>0.000</OffsetZ>
        <Heading>272.0</Heading>
    </FED>
    <FED Num="88">
        <FeatureCtIdx>2039</FeatureCtIdx>
        <OffsetX>4332.559</OffsetX>
        <OffsetY>-5798.123</OffsetY>
        <OffsetZ>0.000</OffsetZ>
        <Heading>227.0</Heading>
    </FED>
    <FED Num="89">
        <FeatureCtIdx>2039</FeatureCtIdx>
        <OffsetX>3799.251</OffsetX>
        <OffsetY>250.756</OffsetY>
        <OffsetZ>0.000</OffsetZ>
        <Heading>245.0</Heading>
    </FED>
    <FED Num="90">
        <FeatureCtIdx>2039</FeatureCtIdx>
        <OffsetX>3986.218</OffsetX>
        <OffsetY>-107.483</OffsetY>
        <OffsetZ>0.000</OffsetZ>
        <Heading>247.0</Heading>
    </FED>
    <FED Num="91">
        <FeatureCtIdx>2043</FeatureCtIdx>
        <OffsetX>4093.322</OffsetX>
        <OffsetY>-6.985</OffsetY>
        <OffsetZ>0.000</OffsetZ>
        <Heading>336.0</Heading>
    </FED>
    <FED Num="92">
        <FeatureCtIdx>2043</FeatureCtIdx>
        <OffsetX>4396.436</OffsetX>
        <OffsetY>-569.313</OffsetY>
        <OffsetZ>0.000</OffsetZ>
        <Heading>336.0</Heading>
    </FED>
    <FED Num="93">
        <FeatureCtIdx>2043</FeatureCtIdx>
        <OffsetX>4296.729</OffsetX>
        <OffsetY>-3612.324</OffsetY>
        <OffsetZ>0.000</OffsetZ>
        <Heading>180.0</Heading>
    </FED>
    <FED Num="94">
        <FeatureCtIdx>2043</FeatureCtIdx>
        <OffsetX>4530.019</OffsetX>
        <OffsetY>-4520.881</OffsetY>
        <OffsetZ>0.000</OffsetZ>
        <Heading>270.0</Heading>
    </FED>
    <FED Num="95">
        <FeatureCtIdx>2043</FeatureCtIdx>
        <OffsetX>4003.134</OffsetX>
        <OffsetY>205.862</OffsetY>
        <OffsetZ>0.000</OffsetZ>
        <Heading>66.0</Heading>
    </FED>
    <FED Num="96">
        <FeatureCtIdx>2044</FeatureCtIdx>
        <OffsetX>4090.906</OffsetX>
        <OffsetY>4.946</OffsetY>
        <OffsetZ>0.000</OffsetZ>
        <Heading>65.0</Heading>
    </FED>
    <FED Num="97">
        <FeatureCtIdx>2044</FeatureCtIdx>
        <OffsetX>4408.810</OffsetX>
        <OffsetY>-584.361</OffsetY>
        <OffsetZ>0.000</OffsetZ>
        <Heading>155.0</Heading>
    </FED>
    <FED Num="98">
        <FeatureCtIdx>2044</FeatureCtIdx>
        <OffsetX>4278.559</OffsetX>
        <OffsetY>-2985.839</OffsetY>
        <OffsetZ>0.000</OffsetZ>
        <Heading>176.0</Heading>
    </FED>
    <FED Num="99">
        <FeatureCtIdx>2044</FeatureCtIdx>
        <OffsetX>4530.183</OffsetX>
        <OffsetY>-4489.724</OffsetY>
        <OffsetZ>0.000</OffsetZ>
        <Heading>92.0</Heading>
    </FED>
    <FED Num="100">
        <FeatureCtIdx>2489</FeatureCtIdx>
        <OffsetX>4112.345</OffsetX>
        <OffsetY>-37.973</OffsetY>
        <OffsetZ>0.000</OffsetZ>
        <Heading>336.0</Heading>
    </FED>
    <FED Num="101">
        <FeatureCtIdx>2489</FeatureCtIdx>
        <OffsetX>4271.544</OffsetX>
        <OffsetY>-411.313</OffsetY>
        <OffsetZ>0.000</OffsetZ>
        <Heading>336.0</Heading>
    </FED>
    <FED Num="102">
        <FeatureCtIdx>2489</FeatureCtIdx>
        <OffsetX>4403.086</OffsetX>
        <OffsetY>-709.767</OffsetY>
        <OffsetZ>0.000</OffsetZ>
        <Heading>336.0</Heading>
    </FED>
    <FED Num="103">
        <FeatureCtIdx>2489</FeatureCtIdx>
        <OffsetX>4853.185</OffsetX>
        <OffsetY>-1880.955</OffsetY>
        <OffsetZ>0.000</OffsetZ>
        <Heading>357.0</Heading>
    </FED>
    <FED Num="104">
        <FeatureCtIdx>2489</FeatureCtIdx>
        <OffsetX>4848.609</OffsetX>
        <OffsetY>-2191.782</OffsetY>
        <OffsetZ>0.000</OffsetZ>
        <Heading>357.0</Heading>
    </FED>
    <FED Num="105">
        <FeatureCtIdx>2489</FeatureCtIdx>
        <OffsetX>4847.015</OffsetX>
        <OffsetY>-2507.666</OffsetY>
        <OffsetZ>0.000</OffsetZ>
        <Heading>357.0</Heading>
    </FED>
    <FED Num="106">
        <FeatureCtIdx>2489</FeatureCtIdx>
        <OffsetX>4848.353</OffsetX>
        <OffsetY>-2865.443</OffsetY>
        <OffsetZ>0.000</OffsetZ>
        <Heading>357.0</Heading>
    </FED>
    <FED Num="107">
        <FeatureCtIdx>2489</FeatureCtIdx>
        <OffsetX>4847.249</OffsetX>
        <OffsetY>-3226.025</OffsetY>
        <OffsetZ>0.000</OffsetZ>
        <Heading>357.0</Heading>
    </FED>
    <FED Num="108">
        <FeatureCtIdx>2489</FeatureCtIdx>
        <OffsetX>4848.769</OffsetX>
        <OffsetY>-3586.425</OffsetY>
        <OffsetZ>0.000</OffsetZ>
        <Heading>357.0</Heading>
    </FED>
    <FED Num="109">
        <FeatureCtIdx>2489</FeatureCtIdx>
        <OffsetX>5133.295</OffsetX>
        <OffsetY>-3638.360</OffsetY>
        <OffsetZ>0.000</OffsetZ>
        <Heading>268.0</Heading>
    </FED>
    <FED Num="110">
        <FeatureCtIdx>2489</FeatureCtIdx>
        <OffsetX>5135.238</OffsetX>
        <OffsetY>-4427.346</OffsetY>
        <OffsetZ>0.000</OffsetZ>
        <Heading>88.0</Heading>
    </FED>
    <FED Num="111">
        <FeatureCtIdx>2489</FeatureCtIdx>
        <OffsetX>5369.990</OffsetX>
        <OffsetY>-3638.854</OffsetY>
        <OffsetZ>0.000</OffsetZ>
        <Heading>268.0</Heading>
    </FED>
    <FED Num="112">
        <FeatureCtIdx>2489</FeatureCtIdx>
        <OffsetX>5373.297</OffsetX>
        <OffsetY>-4434.279</OffsetY>
        <OffsetZ>0.000</OffsetZ>
        <Heading>88.0</Heading>
    </FED>
    <FED Num="113">
        <FeatureCtIdx>2489</FeatureCtIdx>
        <OffsetX>5725.778</OffsetX>
        <OffsetY>-3632.744</OffsetY>
        <OffsetZ>0.000</OffsetZ>
        <Heading>268.0</Heading>
    </FED>
    <FED Num="114">
        <FeatureCtIdx>2489</FeatureCtIdx>
        <OffsetX>5724.224</OffsetX>
        <OffsetY>-4432.844</OffsetY>
        <OffsetZ>0.000</OffsetZ>
        <Heading>88.0</Heading>
    </FED>
    <FED Num="115">
        <FeatureCtIdx>2489</FeatureCtIdx>
        <OffsetX>6143.077</OffsetX>
        <OffsetY>-3637.653</OffsetY>
        <OffsetZ>0.000</OffsetZ>
        <Heading>268.0</Heading>
    </FED>
    <FED Num="116">
        <FeatureCtIdx>2489</FeatureCtIdx>
        <OffsetX>6145.018</OffsetX>
        <OffsetY>-4426.642</OffsetY>
        <OffsetZ>0.000</OffsetZ>
        <Heading>88.0</Heading>
    </FED>
    <FED Num="117">
        <FeatureCtIdx>2489</FeatureCtIdx>
        <OffsetX>3979.351</OffsetX>
        <OffsetY>263.489</OffsetY>
        <OffsetZ>0.000</OffsetZ>
        <Heading>336.0</Heading>
    </FED>
    <FED Num="118">
        <FeatureCtIdx>2544</FeatureCtIdx>
        <Value>30</Value>
        <OffsetX>4117.241</OffsetX>
        <OffsetY>144.461</OffsetY>
        <OffsetZ>0.000</OffsetZ>
        <Heading>66.0</Heading>
    </FED>
    <FED Num="119">
        <FeatureCtIdx>2544</FeatureCtIdx>
        <Value>30</Value>
        <OffsetX>4219.224</OffsetX>
        <OffsetY>-89.515</OffsetY>
        <OffsetZ>0.000</OffsetZ>
        <Heading>66.0</Heading>
    </FED>
    <FED Num="120">
        <FeatureCtIdx>2544</FeatureCtIdx>
        <Value>30</Value>
        <OffsetX>4321.206</OffsetX>
        <OffsetY>-323.492</OffsetY>
        <OffsetZ>0.000</OffsetZ>
        <Heading>66.0</Heading>
    </FED>
    <FED Num="121">
        <FeatureCtIdx>2585</FeatureCtIdx>
        <Value>60</Value>
        <OffsetX>4349.145</OffsetX>
        <OffsetY>-905.800</OffsetY>
        <OffsetZ>0.000</OffsetZ>
        <Heading>157.0</Heading>
    </FED>
    <FED Num="122">
        <FeatureCtIdx>2585</FeatureCtIdx>
        <Value>60</Value>
        <OffsetX>3795.450</OffsetX>
        <OffsetY>-6645.290</OffsetY>
        <OffsetZ>0.000</OffsetZ>
        <Heading>130.0</Heading>
    </FED>
    <FED Num="123">
        <FeatureCtIdx>2585</FeatureCtIdx>
        <Value>60</Value>
        <OffsetX>3795.340</OffsetX>
        <OffsetY>-6971.445</OffsetY>
        <OffsetZ>0.000</OffsetZ>
        <Heading>130.0</Heading>
    </FED>
    <FED Num="124">
        <FeatureCtIdx>2585</FeatureCtIdx>
        <Value>60</Value>
        <OffsetX>4328.446</OffsetX>
        <OffsetY>-6510.241</OffsetY>
        <OffsetZ>0.000</OffsetZ>
        <Heading>50.0</Heading>
    </FED>
    <FED Num="125">
        <FeatureCtIdx>2585</FeatureCtIdx>
        <Value>60</Value>
        <OffsetX>4328.336</OffsetX>
        <OffsetY>-6836.398</OffsetY>
        <OffsetZ>0.000</OffsetZ>
        <Heading>50.0</Heading>
    </FED>
    <FED Num="126">
        <FeatureCtIdx>2602</FeatureCtIdx>
        <Value>70</Value>
        <OffsetX>4968.317</OffsetX>
        <OffsetY>-2712.369</OffsetY>
        <OffsetZ>0.000</OffsetZ>
        <Heading>90.0</Heading>
    </FED>
    <FED Num="127">
        <FeatureCtIdx>2602</FeatureCtIdx>
        <Value>70</Value>
        <OffsetX>6227.589</OffsetX>
        <OffsetY>-4549.467</OffsetY>
        <OffsetZ>0.000</OffsetZ>
        <Heading>180.0</Heading>
    </FED>
    <FED Num="128">
        <FeatureCtIdx>2655</FeatureCtIdx>
        <OffsetX>4387.538</OffsetX>
        <OffsetY>-918.302</OffsetY>
        <OffsetZ>0.000</OffsetZ>
        <Heading>247.0</Heading>
    </FED>
    <FED Num="129">
        <FeatureCtIdx>2656</FeatureCtIdx>
        <OffsetX>4351.573</OffsetX>
        <OffsetY>54.280</OffsetY>
        <OffsetZ>0.000</OffsetZ>
        <Heading>246.0</Heading>
    </FED>
    <FED Num="130">
        <FeatureCtIdx>2656</FeatureCtIdx>
        <OffsetX>4483.768</OffsetX>
        <OffsetY>-242.617</OffsetY>
        <OffsetZ>0.000</OffsetZ>
        <Heading>246.0</Heading>
    </FED>
    <FED Num="131">
        <FeatureCtIdx>2660</FeatureCtIdx>
        <OffsetX>2877.266</OffsetX>
        <OffsetY>-7370.688</OffsetY>
        <OffsetZ>0.000</OffsetZ>
        <Heading>0.0</Heading>
    </FED>
    <FED Num="132">
        <FeatureCtIdx>2661</FeatureCtIdx>
        <OffsetX>5615.738</OffsetX>
        <OffsetY>-2265.677</OffsetY>
        <OffsetZ>0.000</OffsetZ>
        <Heading>180.0</Heading>
    </FED>
    <FED Num="133">
        <FeatureCtIdx>2661</FeatureCtIdx>
        <OffsetX>2246.678</OffsetX>
        <OffsetY>-3481.161</OffsetY>
        <OffsetZ>0.000</OffsetZ>
        <Heading>0.0</Heading>
    </FED>
    <FED Num="134">
        <FeatureCtIdx>2685</FeatureCtIdx>
        <Value>25</Value>
        <OffsetX>3429.226</OffsetX>
        <OffsetY>-6861.001</OffsetY>
        <OffsetZ>0.000</OffsetZ>
        <Heading>0.0</Heading>
    </FED>
    <FED Num="135">
        <FeatureCtIdx>2685</FeatureCtIdx>
        <Value>25</Value>
        <OffsetX>3429.224</OffsetX>
        <OffsetY>-361.004</OffsetY>
        <OffsetZ>0.000</OffsetZ>
        <Heading>180.0</Heading>
    </FED>
    <FED Num="136">
        <FeatureCtIdx>2795</FeatureCtIdx>
        <OffsetX>4305.914</OffsetX>
        <OffsetY>-2694.762</OffsetY>
        <OffsetZ>0.000</OffsetZ>
        <Heading>180.0</Heading>
    </FED>
    <FED Num="137">
        <FeatureCtIdx>2795</FeatureCtIdx>
        <OffsetX>4305.962</OffsetX>
        <OffsetY>-2989.270</OffsetY>
        <OffsetZ>0.000</OffsetZ>
        <Heading>180.0</Heading>
    </FED>
    <FED Num="138">
        <FeatureCtIdx>2795</FeatureCtIdx>
        <OffsetX>4305.949</OffsetX>
        <OffsetY>-3284.740</OffsetY>
        <OffsetZ>0.000</OffsetZ>
        <Heading>180.0</Heading>
    </FED>
    <FED Num="139">
        <FeatureCtIdx>2795</FeatureCtIdx>
        <OffsetX>4306.018</OffsetX>
        <OffsetY>-3580.687</OffsetY>
        <OffsetZ>0.000</OffsetZ>
        <Heading>180.0</Heading>
    </FED>
    <FED Num="140">
        <FeatureCtIdx>2796</FeatureCtIdx>
        <OffsetX>4252.449</OffsetX>
        <OffsetY>-1815.860</OffsetY>
        <OffsetZ>0.000</OffsetZ>
        <Heading>180.0</Heading>
    </FED>
    <FED Num="141">
        <FeatureCtIdx>2796</FeatureCtIdx>
        <OffsetX>4252.563</OffsetX>
        <OffsetY>-2404.896</OffsetY>
        <OffsetZ>0.000</OffsetZ>
        <Heading>180.0</Heading>
    </FED>
    <FED Num="142">
        <FeatureCtIdx>2850</FeatureCtIdx>
        <OffsetX>3519.978</OffsetX>
        <OffsetY>-3932.019</OffsetY>
        <OffsetZ>0.000</OffsetZ>
        <Heading>90.0</Heading>
    </FED>
    <FED Num="143">
        <FeatureCtIdx>2850</FeatureCtIdx>
        <OffsetX>3939.496</OffsetX>
        <OffsetY>-3949.759</OffsetY>
        <OffsetZ>0.000</OffsetZ>
        <Heading>0.0</Heading>
    </FED>
    <FED Num="144">
        <FeatureCtIdx>2850</FeatureCtIdx>
        <OffsetX>4583.885</OffsetX>
        <OffsetY>-4363.581</OffsetY>
        <OffsetZ>0.000</OffsetZ>
        <Heading>0.0</Heading>
    </FED>
    <FED Num="145">
        <FeatureCtIdx>2851</FeatureCtIdx>
        <OffsetX>5030.925</OffsetX>
        <OffsetY>-4420.908</OffsetY>
        <OffsetZ>0.000</OffsetZ>
        <Heading>90.0</Heading>
    </FED>
    <FED Num="146">
        <FeatureCtIdx>2851</FeatureCtIdx>
        <OffsetX>5722.568</OffsetX>
        <OffsetY>-3624.029</OffsetY>
        <OffsetZ>0.000</OffsetZ>
        <Heading>180.0</Heading>
    </FED>
    <FED Num="147">
        <FeatureCtIdx>2852</FeatureCtIdx>
        <OffsetX>3519.934</OffsetX>
        <OffsetY>-3820.210</OffsetY>
        <OffsetZ>0.000</OffsetZ>
        <Heading>90.0</Heading>
    </FED>
    <FED Num="148">
        <FeatureCtIdx>2852</FeatureCtIdx>
        <OffsetX>6442.894</OffsetX>
        <OffsetY>-3467.371</OffsetY>
        <OffsetZ>0.000</OffsetZ>
        <Heading>90.0</Heading>
    </FED>
    <FED Num="149">
        <FeatureCtIdx>2853</FeatureCtIdx>
        <OffsetX>3486.580</OffsetX>
        <OffsetY>-7909.337</OffsetY>
        <OffsetZ>0.000</OffsetZ>
        <Heading>355.0</Heading>
    </FED>
    <FED Num="150">
        <FeatureCtIdx>2853</FeatureCtIdx>
        <OffsetX>3782.109</OffsetX>
        <OffsetY>-6594.725</OffsetY>
        <OffsetZ>0.000</OffsetZ>
        <Heading>133.0</Heading>
    </FED>
    <FED Num="151">
        <FeatureCtIdx>2853</FeatureCtIdx>
        <OffsetX>3778.240</OffsetX>
        <OffsetY>-6918.391</OffsetY>
        <OffsetZ>0.000</OffsetZ>
        <Heading>46.0</Heading>
    </FED>
    <FED Num="152">
        <FeatureCtIdx>2853</FeatureCtIdx>
        <OffsetX>4244.322</OffsetX>
        <OffsetY>-5715.904</OffsetY>
        <OffsetZ>0.000</OffsetZ>
        <Heading>227.0</Heading>
    </FED>
    <FED Num="153">
        <FeatureCtIdx>2853</FeatureCtIdx>
        <OffsetX>4241.529</OffsetX>
        <OffsetY>-6372.326</OffsetY>
        <OffsetZ>0.000</OffsetZ>
        <Heading>315.0</Heading>
    </FED>
    <FED Num="154">
        <FeatureCtIdx>2853</FeatureCtIdx>
        <OffsetX>3495.039</OffsetX>
        <OffsetY>652.459</OffsetY>
        <OffsetZ>0.000</OffsetZ>
        <Heading>349.0</Heading>
    </FED>
    <FED Num="155">
        <FeatureCtIdx>2863</FeatureCtIdx>
        <OffsetX>4000.379</OffsetX>
        <OffsetY>-187.947</OffsetY>
        <OffsetZ>0.000</OffsetZ>
        <Heading>156.0</Heading>
    </FED>
    <FED Num="156">
        <FeatureCtIdx>2863</FeatureCtIdx>
        <OffsetX>4033.827</OffsetX>
        <OffsetY>-264.061</OffsetY>
        <OffsetZ>0.000</OffsetZ>
        <Heading>156.0</Heading>
    </FED>
    <FED Num="157">
        <FeatureCtIdx>2863</FeatureCtIdx>
        <OffsetX>4067.275</OffsetX>
        <OffsetY>-340.184</OffsetY>
        <OffsetZ>0.000</OffsetZ>
        <Heading>156.0</Heading>
    </FED>
    <FED Num="158">
        <FeatureCtIdx>2863</FeatureCtIdx>
        <OffsetX>4100.722</OffsetX>
        <OffsetY>-416.304</OffsetY>
        <OffsetZ>0.000</OffsetZ>
        <Heading>156.0</Heading>
    </FED>
    <FED Num="159">
        <FeatureCtIdx>2863</FeatureCtIdx>
        <OffsetX>4134.171</OffsetX>
        <OffsetY>-492.422</OffsetY>
        <OffsetZ>0.000</OffsetZ>
        <Heading>156.0</Heading>
    </FED>
    <FED Num="160">
        <FeatureCtIdx>2863</FeatureCtIdx>
        <OffsetX>3801.167</OffsetX>
        <OffsetY>-5614.711</OffsetY>
        <OffsetZ>0.000</OffsetZ>
        <Heading>129.0</Heading>
    </FED>
    <FED Num="161">
        <FeatureCtIdx>2863</FeatureCtIdx>
        <OffsetX>4131.404</OffsetX>
        <OffsetY>-3903.177</OffsetY>
        <OffsetZ>0.000</OffsetZ>
        <Heading>347.0</Heading>
    </FED>
    <FED Num="162">
        <FeatureCtIdx>2863</FeatureCtIdx>
        <OffsetX>3783.142</OffsetX>
        <OffsetY>-5941.572</OffsetY>
        <OffsetZ>0.000</OffsetZ>
        <Heading>230.0</Heading>
    </FED>
    <FED Num="163">
        <FeatureCtIdx>2863</FeatureCtIdx>
        <OffsetX>4319.264</OffsetX>
        <OffsetY>-3905.777</OffsetY>
        <OffsetZ>0.000</OffsetZ>
        <Heading>300.0</Heading>
    </FED>
    <FED Num="164">
        <FeatureCtIdx>2863</FeatureCtIdx>
        <OffsetX>4277.599</OffsetX>
        <OffsetY>-5718.771</OffsetY>
        <OffsetZ>0.000</OffsetZ>
        <Heading>317.0</Heading>
    </FED>
    <FED Num="165">
        <FeatureCtIdx>2863</FeatureCtIdx>
        <OffsetX>4247.240</OffsetX>
        <OffsetY>-6041.208</OffsetY>
        <OffsetZ>0.000</OffsetZ>
        <Heading>311.0</Heading>
    </FED>
    <FED Num="166">
        <FeatureCtIdx>2863</FeatureCtIdx>
        <OffsetX>4237.960</OffsetX>
        <OffsetY>-6701.021</OffsetY>
        <OffsetZ>0.000</OffsetZ>
        <Heading>320.0</Heading>
    </FED>
    <FED Num="167">
        <FeatureCtIdx>2863</FeatureCtIdx>
        <OffsetX>3833.142</OffsetX>
        <OffsetY>192.639</OffsetY>
        <OffsetZ>0.000</OffsetZ>
        <Heading>156.0</Heading>
    </FED>
    <FED Num="168">
        <FeatureCtIdx>2863</FeatureCtIdx>
        <OffsetX>3866.589</OffsetX>
        <OffsetY>116.522</OffsetY>
        <OffsetZ>0.000</OffsetZ>
        <Heading>156.0</Heading>
    </FED>
    <FED Num="169">
        <FeatureCtIdx>2863</FeatureCtIdx>
        <OffsetX>3900.033</OffsetX>
        <OffsetY>40.398</OffsetY>
        <OffsetZ>0.000</OffsetZ>
        <Heading>156.0</Heading>
    </FED>
    <FED Num="170">
        <FeatureCtIdx>2863</FeatureCtIdx>
        <OffsetX>3933.480</OffsetX>
        <OffsetY>-35.720</OffsetY>
        <OffsetZ>0.000</OffsetZ>
        <Heading>156.0</Heading>
    </FED>
    <FED Num="171">
        <FeatureCtIdx>2863</FeatureCtIdx>
        <OffsetX>3966.932</OffsetX>
        <OffsetY>-111.829</OffsetY>
        <OffsetZ>0.000</OffsetZ>
        <Heading>156.0</Heading>
    </FED>
    <FED Num="172">
        <FeatureCtIdx>2942</FeatureCtIdx>
        <OffsetX>4346.049</OffsetX>
        <OffsetY>-585.751</OffsetY>
        <OffsetZ>0.000</OffsetZ>
        <Heading>26.0</Heading>
    </FED>
    <FED Num="173">
        <FeatureCtIdx>2942</FeatureCtIdx>
        <OffsetX>3840.292</OffsetX>
        <OffsetY>-4041.920</OffsetY>
        <OffsetZ>0.000</OffsetZ>
        <Heading>280.0</Heading>
    </FED>
    <FED Num="174">
        <FeatureCtIdx>2942</FeatureCtIdx>
        <OffsetX>4003.697</OffsetX>
        <OffsetY>-4529.295</OffsetY>
        <OffsetZ>0.000</OffsetZ>
        <Heading>290.0</Heading>
    </FED>
    <FED Num="175">
        <FeatureCtIdx>2942</FeatureCtIdx>
        <OffsetX>4288.861</OffsetX>
        <OffsetY>-3280.089</OffsetY>
        <OffsetZ>0.000</OffsetZ>
        <Heading>270.0</Heading>
    </FED>
    <FED Num="176">
        <FeatureCtIdx>2942</FeatureCtIdx>
        <OffsetX>3806.951</OffsetX>
        <OffsetY>-6279.988</OffsetY>
        <OffsetZ>0.000</OffsetZ>
        <Heading>263.0</Heading>
    </FED>
    <FED Num="177">
        <FeatureCtIdx>2943</FeatureCtIdx>
        <OffsetX>3997.619</OffsetX>
        <OffsetY>-4023.331</OffsetY>
        <OffsetZ>0.000</OffsetZ>
        <Heading>195.0</Heading>
    </FED>
    <FED Num="178">
        <FeatureCtIdx>2943</FeatureCtIdx>
        <OffsetX>4275.007</OffsetX>
        <OffsetY>-6823.236</OffsetY>
        <OffsetZ>0.000</OffsetZ>
        <Heading>49.0</Heading>
    </FED>
    <FED Num="179">
        <FeatureCtIdx>2944</FeatureCtIdx>
        <OffsetX>3500.806</OffsetX>
        <OffsetY>-7909.130</OffsetY>
        <OffsetZ>0.000</OffsetZ>
        <Heading>89.0</Heading>
    </FED>
    <FED Num="180">
        <FeatureCtIdx>2944</FeatureCtIdx>
        <OffsetX>4530.158</OffsetX>
        <OffsetY>-5094.152</OffsetY>
        <OffsetZ>0.000</OffsetZ>
        <Heading>90.0</Heading>
    </FED>
    <FED Num="181">
        <FeatureCtIdx>2944</FeatureCtIdx>
        <OffsetX>3515.184</OffsetX>
        <OffsetY>636.183</OffsetY>
        <OffsetZ>0.000</OffsetZ>
        <Heading>328.0</Heading>
    </FED>
    <FED Num="182">
        <FeatureCtIdx>3099</FeatureCtIdx>
        <Value>40</Value>
        <OffsetX>4365.375</OffsetX>
        <OffsetY>-5701.004</OffsetY>
        <OffsetZ>0.000</OffsetZ>
        <Heading>230.0</Heading>
    </FED>
    <FED Num="183">
        <FeatureCtIdx>3099</FeatureCtIdx>
        <Value>40</Value>
        <OffsetX>4365.339</OffsetX>
        <OffsetY>-6027.225</OffsetY>
        <OffsetZ>0.000</OffsetZ>
        <Heading>230.0</Heading>
    </FED>
    <FED Num="184">
        <FeatureCtIdx>3099</FeatureCtIdx>
        <Value>40</Value>
        <OffsetX>4365.458</OffsetX>
        <OffsetY>-6353.437</OffsetY>
        <OffsetZ>0.000</OffsetZ>
        <Heading>230.0</Heading>
    </FED>
    <FED Num="185">
        <FeatureCtIdx>3194</FeatureCtIdx>
        <Value>5</Value>
        <OffsetX>4708.207</OffsetX>
        <OffsetY>-3779.177</OffsetY>
        <OffsetZ>0.000</OffsetZ>
        <Heading>270.0</Heading>
    </FED>
    <FED Num="186">
        <FeatureCtIdx>3195</FeatureCtIdx>
        <Value>5</Value>
        <OffsetX>4738.532</OffsetX>
        <OffsetY>-4655.421</OffsetY>
        <OffsetZ>0.000</OffsetZ>
        <Heading>270.0</Heading>
    </FED>
    <FED Num="187">
        <FeatureCtIdx>3203</FeatureCtIdx>
        <Value>5</Value>
        <OffsetX>5038.247</OffsetX>
        <OffsetY>-3534.554</OffsetY>
        <OffsetZ>0.000</OffsetZ>
        <Heading>0.0</Heading>
    </FED>
    <FED Num="188">
        <FeatureCtIdx>3207</FeatureCtIdx>
        <OffsetX>5043.388</OffsetX>
        <OffsetY>-6376.407</OffsetY>
        <OffsetZ>0.000</OffsetZ>
        <Heading>90.0</Heading>
    </FED>
    <FED Num="189">
        <FeatureCtIdx>3531</FeatureCtIdx>
        <OffsetX>4414.627</OffsetX>
        <OffsetY>-541.406</OffsetY>
        <OffsetZ>0.000</OffsetZ>
        <Heading>81.0</Heading>
    </FED>
    <FED Num="190">
        <FeatureCtIdx>3568</FeatureCtIdx>
        <OffsetX>4402.214</OffsetX>
        <OffsetY>-526.127</OffsetY>
        <OffsetZ>0.000</OffsetZ>
        <Heading>336.0</Heading>
    </FED>
    <FED Num="191">
        <FeatureCtIdx>3568</FeatureCtIdx>
        <OffsetX>4297.755</OffsetX>
        <OffsetY>-3018.191</OffsetY>
        <OffsetZ>0.000</OffsetZ>
        <Heading>179.0</Heading>
    </FED>
    <FED Num="192">
        <FeatureCtIdx>3570</FeatureCtIdx>
        <OffsetX>4713.408</OffsetX>
        <OffsetY>-1735.438</OffsetY>
        <OffsetZ>0.000</OffsetZ>
        <Heading>270.0</Heading>
    </FED>
    <FED Num="193">
        <FeatureCtIdx>3570</FeatureCtIdx>
        <OffsetX>5001.548</OffsetX>
        <OffsetY>-4265.751</OffsetY>
        <OffsetZ>0.000</OffsetZ>
        <Heading>180.0</Heading>
    </FED>
    <FED Num="194">
        <FeatureCtIdx>3576</FeatureCtIdx>
        <OffsetX>3940.892</OffsetX>
        <OffsetY>-3728.115</OffsetY>
        <OffsetZ>0.000</OffsetZ>
        <Heading>0.0</Heading>
    </FED>
    <FED Num="195">
        <FeatureCtIdx>3576</FeatureCtIdx>
        <OffsetX>3959.018</OffsetX>
        <OffsetY>-4438.300</OffsetY>
        <OffsetZ>0.000</OffsetZ>
        <Heading>270.0</Heading>
    </FED>
    <FED Num="196">
        <FeatureCtIdx>3576</FeatureCtIdx>
        <OffsetX>4879.055</OffsetX>
        <OffsetY>-2214.511</OffsetY>
        <OffsetZ>0.000</OffsetZ>
        <Heading>90.0</Heading>
    </FED>
    <FED Num="197">
        <FeatureCtIdx>3576</FeatureCtIdx>
        <OffsetX>4559.016</OffsetX>
        <OffsetY>-4709.444</OffsetY>
        <OffsetZ>0.000</OffsetZ>
        <Heading>90.0</Heading>
    </FED>
    <FED Num="198">
        <FeatureCtIdx>3576</FeatureCtIdx>
        <OffsetX>4879.055</OffsetX>
        <OffsetY>-3214.516</OffsetY>
        <OffsetZ>0.000</OffsetZ>
        <Heading>90.0</Heading>
    </FED>
    <FED Num="199">
        <FeatureCtIdx>3577</FeatureCtIdx>
        <Value>35</Value>
        <OffsetX>4415.642</OffsetX>
        <OffsetY>-532.154</OffsetY>
        <OffsetZ>0.000</OffsetZ>
        <Heading>156.0</Heading>
    </FED>
    <FED Num="200">
        <FeatureCtIdx>3580</FeatureCtIdx>
        <OffsetX>3806.111</OffsetX>
        <OffsetY>-4392.153</OffsetY>
        <OffsetZ>0.000</OffsetZ>
        <Heading>90.0</Heading>
    </FED>
    <FED Num="201">
        <FeatureCtIdx>3597</FeatureCtIdx>
        <OffsetX>4447.009</OffsetX>
        <OffsetY>-588.021</OffsetY>
        <OffsetZ>0.000</OffsetZ>
        <Heading>335.0</Heading>
    </FED>
    <FED Num="202">
        <FeatureCtIdx>3597</FeatureCtIdx>
        <OffsetX>4282.440</OffsetX>
        <OffsetY>-2965.323</OffsetY>
        <OffsetZ>0.000</OffsetZ>
        <Heading>179.0</Heading>
    </FED>
    <FED Num="203">
        <FeatureCtIdx>3639</FeatureCtIdx>
        <OffsetX>3179.716</OffsetX>
        <OffsetY>-6412.422</OffsetY>
        <OffsetZ>0.000</OffsetZ>
        <Heading>270.0</Heading>
    </FED>
    <FED Num="204">
        <FeatureCtIdx>3639</FeatureCtIdx>
        <OffsetX>3179.626</OffsetX>
        <OffsetY>-837.425</OffsetY>
        <OffsetZ>0.000</OffsetZ>
        <Heading>90.0</Heading>
    </FED>
    <FED Num="205">
        <FeatureCtIdx>3669</FeatureCtIdx>
        <Value>30</Value>
        <OffsetX>6317.869</OffsetX>
        <OffsetY>-3705.790</OffsetY>
        <OffsetZ>0.000</OffsetZ>
        <Heading>180.0</Heading>
    </FED>
    <FED Num="206">
        <FeatureCtIdx>3669</FeatureCtIdx>
        <Value>30</Value>
        <OffsetX>6317.358</OffsetX>
        <OffsetY>-3820.330</OffsetY>
        <OffsetZ>0.000</OffsetZ>
        <Heading>180.0</Heading>
    </FED>
    <FED Num="207">
        <FeatureCtIdx>3676</FeatureCtIdx>
        <Value>30</Value>
        <OffsetX>5445.655</OffsetX>
        <OffsetY>-3482.287</OffsetY>
        <OffsetZ>0.000</OffsetZ>
        <Heading>0.0</Heading>
    </FED>
    <FED Num="208">
        <FeatureCtIdx>3676</FeatureCtIdx>
        <Value>30</Value>
        <OffsetX>5986.308</OffsetX>
        <OffsetY>-3481.110</OffsetY>
        <OffsetZ>0.000</OffsetZ>
        <Heading>0.0</Heading>
    </FED>
    <FED Num="209">
        <FeatureCtIdx>3720</FeatureCtIdx>
        <OffsetX>5063.387</OffsetX>
        <OffsetY>-3338.926</OffsetY>
        <OffsetZ>0.000</OffsetZ>
        <Heading>270.0</Heading>
    </FED>
    <FED Num="210">
        <FeatureCtIdx>462</FeatureCtIdx>
        <Value>40</Value>
        <OffsetX>3758.683</OffsetX>
        <OffsetY>-5509.673</OffsetY>
        <OffsetZ>0.000</OffsetZ>
        <Heading>130.0</Heading>
    </FED>
    <FED Num="211">
        <FeatureCtIdx>462</FeatureCtIdx>
        <Value>40</Value>
        <OffsetX>3758.694</OffsetX>
        <OffsetY>-5835.973</OffsetY>
        <OffsetZ>0.000</OffsetZ>
        <Heading>130.0</Heading>
    </FED>
    <FED Num="212">
        <FeatureCtIdx>462</FeatureCtIdx>
        <Value>40</Value>
        <OffsetX>3758.807</OffsetX>
        <OffsetY>-6162.188</OffsetY>
        <OffsetZ>0.000</OffsetZ>
        <Heading>130.0</Heading>
    </FED>
    <FED Num="213">
        <FeatureCtIdx>462</FeatureCtIdx>
        <Value>40</Value>
        <OffsetX>3758.882</OffsetX>
        <OffsetY>-6488.591</OffsetY>
        <OffsetZ>0.000</OffsetZ>
        <Heading>130.0</Heading>
    </FED>
    <FED Num="214">
        <FeatureCtIdx>462</FeatureCtIdx>
        <Value>40</Value>
        <OffsetX>3758.697</OffsetX>
        <OffsetY>-6814.713</OffsetY>
        <OffsetZ>0.000</OffsetZ>
        <Heading>130.0</Heading>
    </FED>
    <FED Num="215">
        <FeatureCtIdx>462</FeatureCtIdx>
        <Value>40</Value>
        <OffsetX>4365.535</OffsetX>
        <OffsetY>-5374.591</OffsetY>
        <OffsetZ>0.000</OffsetZ>
        <Heading>230.0</Heading>
    </FED>
    <FED Num="216">
        <FeatureCtIdx>462</FeatureCtIdx>
        <Value>40</Value>
        <OffsetX>4365.310</OffsetX>
        <OffsetY>-6679.633</OffsetY>
        <OffsetZ>0.000</OffsetZ>
        <Heading>230.0</Heading>
    </FED>
    <FED Num="217">
        <FeatureCtIdx>465</FeatureCtIdx>
        <Value>30</Value>
        <OffsetX>6357.858</OffsetX>
        <OffsetY>-4157.089</OffsetY>
        <OffsetZ>0.000</OffsetZ>
        <Heading>0.0</Heading>
    </FED>
    <FED Num="218">
        <FeatureCtIdx>3772</FeatureCtIdx>
        <OffsetX>2516.284</OffsetX>
        <OffsetY>-920.330</OffsetY>
        <OffsetZ>0.000</OffsetZ>
        <Heading>0.0</Heading>
    </FED>
    <FED Num="219">
        <FeatureCtIdx>3772</FeatureCtIdx>
        <OffsetX>2512.098</OffsetX>
        <OffsetY>-788.607</OffsetY>
        <OffsetZ>0.000</OffsetZ>
        <Heading>0.0</Heading>
    </FED>
    <FED Num="220">
        <FeatureCtIdx>589</FeatureCtIdx>
        <OffsetX>5027.993</OffsetX>
        <OffsetY>-3009.202</OffsetY>
        <OffsetZ>0.000</OffsetZ>
        <Heading>180.0</Heading>
    </FED>
    <FED Num="221">
        <FeatureCtIdx>589</FeatureCtIdx>
        <OffsetX>5027.993</OffsetX>
        <OffsetY>-3209.200</OffsetY>
        <OffsetZ>0.000</OffsetZ>
        <Heading>180.0</Heading>
    </FED>
    <FED Num="222">
        <FeatureCtIdx>626</FeatureCtIdx>
        <Value>75</Value>
        <OffsetX>5034.116</OffsetX>
        <OffsetY>-6556.933</OffsetY>
        <OffsetZ>0.000</OffsetZ>
        <Heading>180.0</Heading>
    </FED>
    <FED Num="223">
        <FeatureCtIdx>768</FeatureCtIdx>
        <OffsetX>4006.686</OffsetX>
        <OffsetY>-186.019</OffsetY>
        <OffsetZ>0.000</OffsetZ>
        <Heading>336.0</Heading>
    </FED>
    <FED Num="224">
        <FeatureCtIdx>768</FeatureCtIdx>
        <OffsetX>4040.152</OffsetX>
        <OffsetY>-262.111</OffsetY>
        <OffsetZ>0.000</OffsetZ>
        <Heading>336.0</Heading>
    </FED>
    <FED Num="225">
        <FeatureCtIdx>768</FeatureCtIdx>
        <OffsetX>4073.615</OffsetX>
        <OffsetY>-338.203</OffsetY>
        <OffsetZ>0.000</OffsetZ>
        <Heading>336.0</Heading>
    </FED>
    <FED Num="226">
        <FeatureCtIdx>768</FeatureCtIdx>
        <OffsetX>4333.588</OffsetX>
        <OffsetY>-1716.037</OffsetY>
        <OffsetZ>0.000</OffsetZ>
        <Heading>173.0</Heading>
    </FED>
    <FED Num="227">
        <FeatureCtIdx>768</FeatureCtIdx>
        <OffsetX>3811.268</OffsetX>
        <OffsetY>-5623.632</OffsetY>
        <OffsetZ>0.000</OffsetZ>
        <Heading>219.0</Heading>
    </FED>
    <FED Num="228">
        <FeatureCtIdx>768</FeatureCtIdx>
        <OffsetX>3802.330</OffsetX>
        <OffsetY>-5942.366</OffsetY>
        <OffsetZ>0.000</OffsetZ>
        <Heading>219.0</Heading>
    </FED>
    <FED Num="229">
        <FeatureCtIdx>768</FeatureCtIdx>
        <OffsetX>3800.894</OffsetX>
        <OffsetY>-6594.763</OffsetY>
        <OffsetZ>0.000</OffsetZ>
        <Heading>219.0</Heading>
    </FED>
    <FED Num="230">
        <FeatureCtIdx>768</FeatureCtIdx>
        <OffsetX>3789.742</OffsetX>
        <OffsetY>-6928.996</OffsetY>
        <OffsetZ>0.000</OffsetZ>
        <Heading>336.0</Heading>
    </FED>
    <FED Num="231">
        <FeatureCtIdx>768</FeatureCtIdx>
        <OffsetX>4312.460</OffsetX>
        <OffsetY>-5814.210</OffsetY>
        <OffsetZ>0.000</OffsetZ>
        <Heading>318.0</Heading>
    </FED>
    <FED Num="232">
        <FeatureCtIdx>768</FeatureCtIdx>
        <OffsetX>4312.556</OffsetX>
        <OffsetY>-6141.308</OffsetY>
        <OffsetZ>0.000</OffsetZ>
        <Heading>318.0</Heading>
    </FED>
    <FED Num="233">
        <FeatureCtIdx>768</FeatureCtIdx>
        <OffsetX>4312.129</OffsetX>
        <OffsetY>-6467.168</OffsetY>
        <OffsetZ>0.000</OffsetZ>
        <Heading>318.0</Heading>
    </FED>
    <FED Num="234">
        <FeatureCtIdx>768</FeatureCtIdx>
        <OffsetX>4304.001</OffsetX>
        <OffsetY>-6801.557</OffsetY>
        <OffsetZ>0.000</OffsetZ>
        <Heading>318.0</Heading>
    </FED>
    <FED Num="235">
        <FeatureCtIdx>768</FeatureCtIdx>
        <OffsetX>3839.365</OffsetX>
        <OffsetY>194.413</OffsetY>
        <OffsetZ>0.000</OffsetZ>
        <Heading>336.0</Heading>
    </FED>
    <FED Num="236">
        <FeatureCtIdx>768</FeatureCtIdx>
        <OffsetX>3872.828</OffsetX>
        <OffsetY>118.322</OffsetY>
        <OffsetZ>0.000</OffsetZ>
        <Heading>336.0</Heading>
    </FED>
    <FED Num="237">
        <FeatureCtIdx>768</FeatureCtIdx>
        <OffsetX>3932.630</OffsetX>
        <OffsetY>306.001</OffsetY>
        <OffsetZ>0.000</OffsetZ>
        <Heading>334.0</Heading>
    </FED>
    <FED Num="238">
        <FeatureCtIdx>768</FeatureCtIdx>
        <OffsetX>3906.292</OffsetX>
        <OffsetY>42.238</OffsetY>
        <OffsetZ>0.000</OffsetZ>
        <Heading>336.0</Heading>
    </FED>
    <FED Num="239">
        <FeatureCtIdx>768</FeatureCtIdx>
        <OffsetX>3939.761</OffsetX>
        <OffsetY>-33.852</OffsetY>
        <OffsetZ>0.000</OffsetZ>
        <Heading>336.0</Heading>
    </FED>
    <FED Num="240">
        <FeatureCtIdx>768</FeatureCtIdx>
        <OffsetX>3973.223</OffsetX>
        <OffsetY>-109.939</OffsetY>
        <OffsetZ>0.000</OffsetZ>
        <Heading>336.0</Heading>
    </FED>
    <FED Num="241">
        <FeatureCtIdx>896</FeatureCtIdx>
        <OffsetX>3421.533</OffsetX>
        <OffsetY>-7339.621</OffsetY>
        <OffsetZ>0.000</OffsetZ>
        <Heading>280.0</Heading>
    </FED>
    <FED Num="242">
        <FeatureCtIdx>896</FeatureCtIdx>
        <OffsetX>3425.729</OffsetX>
        <OffsetY>-23.368</OffsetY>
        <OffsetZ>0.000</OffsetZ>
        <Heading>280.0</Heading>
    </FED>
    <FED Num="243">
        <FeatureCtIdx>90</FeatureCtIdx>
        <Value>30</Value>
        <OffsetX>5547.434</OffsetX>
        <OffsetY>-4519.879</OffsetY>
        <OffsetZ>0.000</OffsetZ>
        <Heading>0.0</Heading>
    </FED>
    <FED Num="244">
        <FeatureCtIdx>90</FeatureCtIdx>
        <Value>30</Value>
        <OffsetX>5904.669</OffsetX>
        <OffsetY>-4520.545</OffsetY>
        <OffsetZ>0.000</OffsetZ>
        <Heading>0.0</Heading>
    </FED>
</FEDRecords>
