<?xml version="1.0" encoding="utf-8"?>
<FEDRecords>
    <FED Num="0">
        <FeatureCtIdx>3216</FeatureCtIdx>
        <OffsetX>5443.711</OffsetX>
        <OffsetY>1427.287</OffsetY>
        <OffsetZ>0.000</OffsetZ>
        <Heading>331.0</Heading>
    </FED>
    <FED Num="1">
        <FeatureCtIdx>1419</FeatureCtIdx>
        <OffsetX>1450.650</OffsetX>
        <OffsetY>5130.514</OffsetY>
        <OffsetZ>0.000</OffsetZ>
        <Heading>74.0</Heading>
    </FED>
    <FED Num="2">
        <FeatureCtIdx>1419</FeatureCtIdx>
        <OffsetX>1577.590</OffsetX>
        <OffsetY>5171.276</OffsetY>
        <OffsetZ>0.000</OffsetZ>
        <Heading>74.0</Heading>
    </FED>
    <FED Num="3">
        <FeatureCtIdx>2386</FeatureCtIdx>
        <OffsetX>8415.604</OffsetX>
        <OffsetY>4623.667</OffsetY>
        <OffsetZ>0.000</OffsetZ>
        <Heading>205.0</Heading>
    </FED>
    <FED Num="4">
        <FeatureCtIdx>2386</FeatureCtIdx>
        <OffsetX>8455.857</OffsetX>
        <OffsetY>4604.848</OffsetY>
        <OffsetZ>0.000</OffsetZ>
        <Heading>25.0</Heading>
    </FED>
    <FED Num="5">
        <FeatureCtIdx>2386</FeatureCtIdx>
        <OffsetX>8496.706</OffsetX>
        <OffsetY>4583.952</OffsetY>
        <OffsetZ>0.000</OffsetZ>
        <Heading>205.0</Heading>
    </FED>
    <FED Num="6">
        <FeatureCtIdx>2386</FeatureCtIdx>
        <OffsetX>8539.633</OffsetX>
        <OffsetY>4563.653</OffsetY>
        <OffsetZ>0.000</OffsetZ>
        <Heading>25.0</Heading>
    </FED>
    <FED Num="7">
        <FeatureCtIdx>2386</FeatureCtIdx>
        <OffsetX>8580.366</OffsetX>
        <OffsetY>4544.758</OffsetY>
        <OffsetZ>0.000</OffsetZ>
        <Heading>205.0</Heading>
    </FED>
    <FED Num="8">
        <FeatureCtIdx>2386</FeatureCtIdx>
        <OffsetX>8619.812</OffsetX>
        <OffsetY>4524.661</OffsetY>
        <OffsetZ>0.000</OffsetZ>
        <Heading>25.0</Heading>
    </FED>
    <FED Num="9">
        <FeatureCtIdx>2385</FeatureCtIdx>
        <OffsetX>7844.596</OffsetX>
        <OffsetY>5988.437</OffsetY>
        <OffsetZ>0.000</OffsetZ>
        <Heading>3.0</Heading>
    </FED>
    <FED Num="10">
        <FeatureCtIdx>1279</FeatureCtIdx>
        <OffsetX>8545.923</OffsetX>
        <OffsetY>4326.373</OffsetY>
        <OffsetZ>0.000</OffsetZ>
        <Heading>296.0</Heading>
    </FED>
    <FED Num="11">
        <FeatureCtIdx>1370</FeatureCtIdx>
        <OffsetX>-495.620</OffsetX>
        <OffsetY>-6108.799</OffsetY>
        <OffsetZ>0.000</OffsetZ>
        <Heading>24.0</Heading>
    </FED>
    <FED Num="12">
        <FeatureCtIdx>3682</FeatureCtIdx>
        <OffsetX>-739.000</OffsetX>
        <OffsetY>-3440.999</OffsetY>
        <OffsetZ>0.000</OffsetZ>
        <Heading>62.0</Heading>
    </FED>
    <FED Num="13">
        <FeatureCtIdx>1343</FeatureCtIdx>
        <OffsetX>-725.395</OffsetX>
        <OffsetY>3839.367</OffsetY>
        <OffsetZ>0.000</OffsetZ>
        <Heading>242.0</Heading>
    </FED>
    <FED Num="14">
        <FeatureCtIdx>1369</FeatureCtIdx>
        <OffsetX>4983.931</OffsetX>
        <OffsetY>1365.186</OffsetY>
        <OffsetZ>0.000</OffsetZ>
        <Heading>241.0</Heading>
    </FED>
    <FED Num="15">
        <FeatureCtIdx>3680</FeatureCtIdx>
        <OffsetX>2190.433</OffsetX>
        <OffsetY>-546.916</OffsetY>
        <OffsetZ>0.000</OffsetZ>
        <Heading>5.0</Heading>
    </FED>
    <FED Num="16">
        <FeatureCtIdx>888</FeatureCtIdx>
        <OffsetX>6981.954</OffsetX>
        <OffsetY>3120.203</OffsetY>
        <OffsetZ>0.000</OffsetZ>
        <Heading>37.0</Heading>
    </FED>
    <FED Num="17">
        <FeatureCtIdx>589</FeatureCtIdx>
        <OffsetX>5395.696</OffsetX>
        <OffsetY>579.685</OffsetY>
        <OffsetZ>0.000</OffsetZ>
        <Heading>104.0</Heading>
    </FED>
    <FED Num="18">
        <FeatureCtIdx>589</FeatureCtIdx>
        <OffsetX>5354.313</OffsetX>
        <OffsetY>656.088</OffsetY>
        <OffsetZ>0.000</OffsetZ>
        <Heading>14.0</Heading>
    </FED>
    <FED Num="19">
        <FeatureCtIdx>589</FeatureCtIdx>
        <OffsetX>5201.113</OffsetX>
        <OffsetY>197.323</OffsetY>
        <OffsetZ>0.000</OffsetZ>
        <Heading>14.0</Heading>
    </FED>
    <FED Num="20">
        <FeatureCtIdx>589</FeatureCtIdx>
        <OffsetX>4251.097</OffsetX>
        <OffsetY>449.695</OffsetY>
        <OffsetZ>0.000</OffsetZ>
        <Heading>331.0</Heading>
    </FED>
    <FED Num="21">
        <FeatureCtIdx>589</FeatureCtIdx>
        <OffsetX>3974.374</OffsetX>
        <OffsetY>566.109</OffsetY>
        <OffsetZ>0.000</OffsetZ>
        <Heading>331.0</Heading>
    </FED>
    <FED Num="22">
        <FeatureCtIdx>589</FeatureCtIdx>
        <OffsetX>4174.460</OffsetX>
        <OffsetY>673.446</OffsetY>
        <OffsetZ>0.000</OffsetZ>
        <Heading>331.0</Heading>
    </FED>
    <FED Num="23">
        <FeatureCtIdx>3227</FeatureCtIdx>
        <OffsetX>-563.559</OffsetX>
        <OffsetY>-1141.704</OffsetY>
        <OffsetZ>0.000</OffsetZ>
        <Heading>329.0</Heading>
    </FED>
    <FED Num="24">
        <FeatureCtIdx>3193</FeatureCtIdx>
        <OffsetX>3690.686</OffsetX>
        <OffsetY>1061.246</OffsetY>
        <OffsetZ>0.000</OffsetZ>
        <Heading>332.0</Heading>
    </FED>
    <FED Num="25">
        <FeatureCtIdx>3226</FeatureCtIdx>
        <OffsetX>3392.613</OffsetX>
        <OffsetY>883.421</OffsetY>
        <OffsetZ>0.000</OffsetZ>
        <Heading>332.0</Heading>
    </FED>
    <FED Num="26">
        <FeatureCtIdx>3214</FeatureCtIdx>
        <OffsetX>3445.879</OffsetX>
        <OffsetY>908.635</OffsetY>
        <OffsetZ>0.000</OffsetZ>
        <Heading>242.0</Heading>
    </FED>
    <FED Num="27">
        <FeatureCtIdx>3193</FeatureCtIdx>
        <OffsetX>-1079.475</OffsetX>
        <OffsetY>2930.617</OffsetY>
        <OffsetZ>0.000</OffsetZ>
        <Heading>64.0</Heading>
    </FED>
    <FED Num="28">
        <FeatureCtIdx>3193</FeatureCtIdx>
        <OffsetX>-229.348</OffsetX>
        <OffsetY>3760.351</OffsetY>
        <OffsetZ>0.000</OffsetZ>
        <Heading>331.0</Heading>
    </FED>
    <FED Num="29">
        <FeatureCtIdx>3227</FeatureCtIdx>
        <OffsetX>7388.509</OffsetX>
        <OffsetY>2691.524</OffsetY>
        <OffsetZ>0.000</OffsetZ>
        <Heading>239.0</Heading>
    </FED>
    <FED Num="30">
        <FeatureCtIdx>3214</FeatureCtIdx>
        <OffsetX>3596.717</OffsetX>
        <OffsetY>616.750</OffsetY>
        <OffsetZ>0.000</OffsetZ>
        <Heading>243.0</Heading>
    </FED>
    <FED Num="31">
        <FeatureCtIdx>3207</FeatureCtIdx>
        <OffsetX>5285.659</OffsetX>
        <OffsetY>1890.127</OffsetY>
        <OffsetZ>0.000</OffsetZ>
        <Heading>331.0</Heading>
    </FED>
    <FED Num="32">
        <FeatureCtIdx>589</FeatureCtIdx>
        <OffsetX>2559.235</OffsetX>
        <OffsetY>159.155</OffsetY>
        <OffsetZ>0.000</OffsetZ>
        <Heading>63.0</Heading>
    </FED>
    <FED Num="33">
        <FeatureCtIdx>589</FeatureCtIdx>
        <OffsetX>3613.496</OffsetX>
        <OffsetY>-112.791</OffsetY>
        <OffsetZ>0.000</OffsetZ>
        <Heading>61.0</Heading>
    </FED>
    <FED Num="34">
        <FeatureCtIdx>589</FeatureCtIdx>
        <OffsetX>3784.619</OffsetX>
        <OffsetY>789.126</OffsetY>
        <OffsetZ>0.000</OffsetZ>
        <Heading>58.0</Heading>
    </FED>
    <FED Num="35">
        <FeatureCtIdx>589</FeatureCtIdx>
        <OffsetX>5813.548</OffsetX>
        <OffsetY>1856.503</OffsetY>
        <OffsetZ>0.000</OffsetZ>
        <Heading>58.0</Heading>
    </FED>
    <FED Num="36">
        <FeatureCtIdx>589</FeatureCtIdx>
        <OffsetX>5181.146</OffsetX>
        <OffsetY>1120.209</OffsetY>
        <OffsetZ>0.000</OffsetZ>
        <Heading>58.0</Heading>
    </FED>
    <FED Num="37">
        <FeatureCtIdx>589</FeatureCtIdx>
        <OffsetX>2427.607</OffsetX>
        <OffsetY>4677.354</OffsetY>
        <OffsetZ>0.000</OffsetZ>
        <Heading>152.0</Heading>
    </FED>
    <FED Num="38">
        <FeatureCtIdx>589</FeatureCtIdx>
        <OffsetX>3059.508</OffsetX>
        <OffsetY>4810.015</OffsetY>
        <OffsetZ>0.000</OffsetZ>
        <Heading>152.0</Heading>
    </FED>
    <FED Num="39">
        <FeatureCtIdx>589</FeatureCtIdx>
        <OffsetX>-1795.138</OffsetX>
        <OffsetY>2733.166</OffsetY>
        <OffsetZ>0.000</OffsetZ>
        <Heading>152.0</Heading>
    </FED>
    <FED Num="40">
        <FeatureCtIdx>589</FeatureCtIdx>
        <OffsetX>-462.482</OffsetX>
        <OffsetY>3489.020</OffsetY>
        <OffsetZ>0.000</OffsetZ>
        <Heading>242.0</Heading>
    </FED>
    <FED Num="41">
        <FeatureCtIdx>589</FeatureCtIdx>
        <OffsetX>256.625</OffsetX>
        <OffsetY>3834.701</OffsetY>
        <OffsetZ>0.000</OffsetZ>
        <Heading>152.0</Heading>
    </FED>
    <FED Num="42">
        <FeatureCtIdx>589</FeatureCtIdx>
        <OffsetX>3206.834</OffsetX>
        <OffsetY>410.945</OffsetY>
        <OffsetZ>0.000</OffsetZ>
        <Heading>63.0</Heading>
    </FED>
    <FED Num="43">
        <FeatureCtIdx>589</FeatureCtIdx>
        <OffsetX>3450.694</OffsetX>
        <OffsetY>536.064</OffsetY>
        <OffsetZ>0.000</OffsetZ>
        <Heading>65.0</Heading>
    </FED>
    <FED Num="44">
        <FeatureCtIdx>589</FeatureCtIdx>
        <OffsetX>4205.904</OffsetX>
        <OffsetY>892.692</OffsetY>
        <OffsetZ>0.000</OffsetZ>
        <Heading>151.0</Heading>
    </FED>
    <FED Num="45">
        <FeatureCtIdx>3214</FeatureCtIdx>
        <OffsetX>4595.901</OffsetX>
        <OffsetY>308.904</OffsetY>
        <OffsetZ>0.000</OffsetZ>
        <Heading>242.0</Heading>
    </FED>
    <FED Num="46">
        <FeatureCtIdx>3214</FeatureCtIdx>
        <OffsetX>3585.011</OffsetX>
        <OffsetY>366.734</OffsetY>
        <OffsetZ>0.000</OffsetZ>
        <Heading>151.0</Heading>
    </FED>
    <FED Num="47">
        <FeatureCtIdx>2911</FeatureCtIdx>
        <OffsetX>-1698.778</OffsetX>
        <OffsetY>-811.364</OffsetY>
        <OffsetZ>0.000</OffsetZ>
        <Heading>235.0</Heading>
    </FED>
    <FED Num="48">
        <FeatureCtIdx>2911</FeatureCtIdx>
        <OffsetX>5833.628</OffsetX>
        <OffsetY>3237.746</OffsetY>
        <OffsetZ>0.000</OffsetZ>
        <Heading>70.0</Heading>
    </FED>
    <FED Num="49">
        <FeatureCtIdx>589</FeatureCtIdx>
        <OffsetX>1765.530</OffsetX>
        <OffsetY>5226.947</OffsetY>
        <OffsetZ>0.000</OffsetZ>
        <Heading>163.0</Heading>
    </FED>
    <FED Num="50">
        <FeatureCtIdx>2656</FeatureCtIdx>
        <OffsetX>5647.974</OffsetX>
        <OffsetY>7302.399</OffsetY>
        <OffsetZ>0.000</OffsetZ>
        <Heading>300.0</Heading>
    </FED>
    <FED Num="51">
        <FeatureCtIdx>2656</FeatureCtIdx>
        <OffsetX>4699.048</OffsetX>
        <OffsetY>6353.850</OffsetY>
        <OffsetZ>0.000</OffsetZ>
        <Heading>310.0</Heading>
    </FED>
    <FED Num="52">
        <FeatureCtIdx>2656</FeatureCtIdx>
        <OffsetX>5422.075</OffsetX>
        <OffsetY>6919.657</OffsetY>
        <OffsetZ>0.000</OffsetZ>
        <Heading>300.0</Heading>
    </FED>
    <FED Num="53">
        <FeatureCtIdx>3640</FeatureCtIdx>
        <OffsetX>4886.248</OffsetX>
        <OffsetY>6780.901</OffsetY>
        <OffsetZ>0.000</OffsetZ>
        <Heading>300.0</Heading>
    </FED>
    <FED Num="54">
        <FeatureCtIdx>3640</FeatureCtIdx>
        <OffsetX>4621.437</OffsetX>
        <OffsetY>6410.180</OffsetY>
        <OffsetZ>0.000</OffsetZ>
        <Heading>310.0</Heading>
    </FED>
    <FED Num="55">
        <FeatureCtIdx>2633</FeatureCtIdx>
        <OffsetX>3850.454</OffsetX>
        <OffsetY>6209.236</OffsetY>
        <OffsetZ>0.000</OffsetZ>
        <Heading>160.0</Heading>
    </FED>
    <FED Num="56">
        <FeatureCtIdx>2955</FeatureCtIdx>
        <OffsetX>-1720.552</OffsetX>
        <OffsetY>2308.749</OffsetY>
        <OffsetZ>0.000</OffsetZ>
        <Heading>57.0</Heading>
    </FED>
    <FED Num="57">
        <FeatureCtIdx>452</FeatureCtIdx>
        <OffsetX>3010.403</OffsetX>
        <OffsetY>377.279</OffsetY>
        <OffsetZ>0.000</OffsetZ>
        <Heading>332.0</Heading>
    </FED>
    <FED Num="58">
        <FeatureCtIdx>2954</FeatureCtIdx>
        <OffsetX>3989.304</OffsetX>
        <OffsetY>-509.770</OffsetY>
        <OffsetZ>0.000</OffsetZ>
        <Heading>61.0</Heading>
    </FED>
    <FED Num="59">
        <FeatureCtIdx>1387</FeatureCtIdx>
        <OffsetX>3399.226</OffsetX>
        <OffsetY>123.502</OffsetY>
        <OffsetZ>0.000</OffsetZ>
        <Heading>242.0</Heading>
    </FED>
    <FED Num="60">
        <FeatureCtIdx>2953</FeatureCtIdx>
        <OffsetX>4305.447</OffsetX>
        <OffsetY>621.408</OffsetY>
        <OffsetZ>0.000</OffsetZ>
        <Heading>61.0</Heading>
    </FED>
    <FED Num="61">
        <FeatureCtIdx>2953</FeatureCtIdx>
        <OffsetX>4543.614</OffsetX>
        <OffsetY>805.742</OffsetY>
        <OffsetZ>0.000</OffsetZ>
        <Heading>330.0</Heading>
    </FED>
    <FED Num="62">
        <FeatureCtIdx>2953</FeatureCtIdx>
        <OffsetX>3928.178</OffsetX>
        <OffsetY>-231.837</OffsetY>
        <OffsetZ>0.000</OffsetZ>
        <Heading>332.0</Heading>
    </FED>
    <FED Num="63">
        <FeatureCtIdx>2953</FeatureCtIdx>
        <OffsetX>3713.784</OffsetX>
        <OffsetY>-333.238</OffsetY>
        <OffsetZ>0.000</OffsetZ>
        <Heading>63.0</Heading>
    </FED>
    <FED Num="64">
        <FeatureCtIdx>2954</FeatureCtIdx>
        <OffsetX>999.256</OffsetX>
        <OffsetY>3892.100</OffsetY>
        <OffsetZ>0.000</OffsetZ>
        <Heading>332.0</Heading>
    </FED>
    <FED Num="65">
        <FeatureCtIdx>2563</FeatureCtIdx>
        <OffsetX>4583.060</OffsetX>
        <OffsetY>-284.995</OffsetY>
        <OffsetZ>0.000</OffsetZ>
        <Heading>355.0</Heading>
    </FED>
    <FED Num="66">
        <FeatureCtIdx>2563</FeatureCtIdx>
        <OffsetX>4769.971</OffsetX>
        <OffsetY>-323.116</OffsetY>
        <OffsetZ>0.000</OffsetZ>
        <Heading>26.0</Heading>
    </FED>
    <FED Num="67">
        <FeatureCtIdx>2563</FeatureCtIdx>
        <OffsetX>4396.375</OffsetX>
        <OffsetY>-270.832</OffsetY>
        <OffsetZ>0.000</OffsetZ>
        <Heading>14.0</Heading>
    </FED>
    <FED Num="68">
        <FeatureCtIdx>2563</FeatureCtIdx>
        <OffsetX>4536.563</OffsetX>
        <OffsetY>-135.106</OffsetY>
        <OffsetZ>0.000</OffsetZ>
        <Heading>333.0</Heading>
    </FED>
    <FED Num="69">
        <FeatureCtIdx>2563</FeatureCtIdx>
        <OffsetX>4716.839</OffsetX>
        <OffsetY>-130.375</OffsetY>
        <OffsetZ>0.000</OffsetZ>
        <Heading>14.0</Heading>
    </FED>
    <FED Num="70">
        <FeatureCtIdx>2563</FeatureCtIdx>
        <OffsetX>4922.505</OffsetX>
        <OffsetY>-315.654</OffsetY>
        <OffsetZ>0.000</OffsetZ>
        <Heading>41.0</Heading>
    </FED>
    <FED Num="71">
        <FeatureCtIdx>2563</FeatureCtIdx>
        <OffsetX>5167.049</OffsetX>
        <OffsetY>108.121</OffsetY>
        <OffsetZ>0.000</OffsetZ>
        <Heading>15.0</Heading>
    </FED>
    <FED Num="72">
        <FeatureCtIdx>2563</FeatureCtIdx>
        <OffsetX>4956.284</OffsetX>
        <OffsetY>12.229</OffsetY>
        <OffsetZ>0.000</OffsetZ>
        <Heading>289.0</Heading>
    </FED>
    <FED Num="73">
        <FeatureCtIdx>2564</FeatureCtIdx>
        <OffsetX>5027.409</OffsetX>
        <OffsetY>-245.286</OffsetY>
        <OffsetZ>0.000</OffsetZ>
        <Heading>209.0</Heading>
    </FED>
    <FED Num="74">
        <FeatureCtIdx>2564</FeatureCtIdx>
        <OffsetX>5082.579</OffsetX>
        <OffsetY>-138.831</OffsetY>
        <OffsetZ>0.000</OffsetZ>
        <Heading>205.0</Heading>
    </FED>
    <FED Num="75">
        <FeatureCtIdx>2564</FeatureCtIdx>
        <OffsetX>5132.804</OffsetX>
        <OffsetY>-20.511</OffsetY>
        <OffsetZ>0.000</OffsetZ>
        <Heading>201.0</Heading>
    </FED>
    <FED Num="76">
        <FeatureCtIdx>2563</FeatureCtIdx>
        <OffsetX>-2559.994</OffsetX>
        <OffsetY>1526.622</OffsetY>
        <OffsetZ>0.000</OffsetZ>
        <Heading>328.0</Heading>
    </FED>
    <FED Num="77">
        <FeatureCtIdx>2563</FeatureCtIdx>
        <OffsetX>4849.468</OffsetX>
        <OffsetY>522.385</OffsetY>
        <OffsetZ>0.000</OffsetZ>
        <Heading>16.0</Heading>
    </FED>
    <FED Num="78">
        <FeatureCtIdx>2563</FeatureCtIdx>
        <OffsetX>4682.892</OffsetX>
        <OffsetY>506.303</OffsetY>
        <OffsetZ>0.000</OffsetZ>
        <Heading>333.0</Heading>
    </FED>
    <FED Num="79">
        <FeatureCtIdx>2563</FeatureCtIdx>
        <OffsetX>4268.808</OffsetX>
        <OffsetY>295.879</OffsetY>
        <OffsetZ>0.000</OffsetZ>
        <Heading>329.0</Heading>
    </FED>
    <FED Num="80">
        <FeatureCtIdx>2563</FeatureCtIdx>
        <OffsetX>4447.377</OffsetX>
        <OffsetY>397.592</OffsetY>
        <OffsetZ>0.000</OffsetZ>
        <Heading>329.0</Heading>
    </FED>
    <FED Num="81">
        <FeatureCtIdx>2563</FeatureCtIdx>
        <OffsetX>4799.226</OffsetX>
        <OffsetY>-2.890</OffsetY>
        <OffsetZ>0.000</OffsetZ>
        <Heading>331.0</Heading>
    </FED>
    <FED Num="82">
        <FeatureCtIdx>2563</FeatureCtIdx>
        <OffsetX>4661.225</OffsetX>
        <OffsetY>-861.723</OffsetY>
        <OffsetZ>0.000</OffsetZ>
        <Heading>12.0</Heading>
    </FED>
    <FED Num="83">
        <FeatureCtIdx>2563</FeatureCtIdx>
        <OffsetX>4527.285</OffsetX>
        <OffsetY>-1059.207</OffsetY>
        <OffsetZ>0.000</OffsetZ>
        <Heading>12.0</Heading>
    </FED>
    <FED Num="84">
        <FeatureCtIdx>2563</FeatureCtIdx>
        <OffsetX>4296.581</OffsetX>
        <OffsetY>-1143.234</OffsetY>
        <OffsetZ>0.000</OffsetZ>
        <Heading>12.0</Heading>
    </FED>
    <FED Num="85">
        <FeatureCtIdx>2563</FeatureCtIdx>
        <OffsetX>4269.129</OffsetX>
        <OffsetY>-1000.488</OffsetY>
        <OffsetZ>0.000</OffsetZ>
        <Heading>12.0</Heading>
    </FED>
    <FED Num="86">
        <FeatureCtIdx>2563</FeatureCtIdx>
        <OffsetX>4418.856</OffsetX>
        <OffsetY>-889.945</OffsetY>
        <OffsetZ>0.000</OffsetZ>
        <Heading>12.0</Heading>
    </FED>
    <FED Num="87">
        <FeatureCtIdx>3676</FeatureCtIdx>
        <OffsetX>-4134.246</OffsetX>
        <OffsetY>739.586</OffsetY>
        <OffsetZ>0.000</OffsetZ>
        <Heading>295.0</Heading>
    </FED>
    <FED Num="88">
        <FeatureCtIdx>3676</FeatureCtIdx>
        <OffsetX>-3925.268</OffsetX>
        <OffsetY>1187.667</OffsetY>
        <OffsetZ>0.000</OffsetZ>
        <Heading>295.0</Heading>
    </FED>
    <FED Num="89">
        <FeatureCtIdx>3671</FeatureCtIdx>
        <OffsetX>-3605.276</OffsetX>
        <OffsetY>1797.047</OffsetY>
        <OffsetZ>0.000</OffsetZ>
        <Heading>26.0</Heading>
    </FED>
    <FED Num="90">
        <FeatureCtIdx>466</FeatureCtIdx>
        <OffsetX>2064.029</OffsetX>
        <OffsetY>-452.966</OffsetY>
        <OffsetZ>0.000</OffsetZ>
        <Heading>185.0</Heading>
    </FED>
    <FED Num="91">
        <FeatureCtIdx>466</FeatureCtIdx>
        <OffsetX>1989.351</OffsetX>
        <OffsetY>-446.685</OffsetY>
        <OffsetZ>0.000</OffsetZ>
        <Heading>185.0</Heading>
    </FED>
    <FED Num="92">
        <FeatureCtIdx>466</FeatureCtIdx>
        <OffsetX>1914.674</OffsetX>
        <OffsetY>-440.404</OffsetY>
        <OffsetZ>0.000</OffsetZ>
        <Heading>185.0</Heading>
    </FED>
    <FED Num="93">
        <FeatureCtIdx>466</FeatureCtIdx>
        <OffsetX>2181.423</OffsetX>
        <OffsetY>4262.759</OffsetY>
        <OffsetZ>0.000</OffsetZ>
        <Heading>242.0</Heading>
    </FED>
    <FED Num="94">
        <FeatureCtIdx>2907</FeatureCtIdx>
        <OffsetX>-903.500</OffsetX>
        <OffsetY>2601.461</OffsetY>
        <OffsetZ>0.000</OffsetZ>
        <Heading>242.0</Heading>
    </FED>
    <FED Num="95">
        <FeatureCtIdx>3733</FeatureCtIdx>
        <OffsetX>2386.302</OffsetX>
        <OffsetY>-979.616</OffsetY>
        <OffsetZ>0.000</OffsetZ>
        <Heading>186.0</Heading>
    </FED>
    <FED Num="96">
        <FeatureCtIdx>3669</FeatureCtIdx>
        <OffsetX>4023.262</OffsetX>
        <OffsetY>743.739</OffsetY>
        <OffsetZ>0.000</OffsetZ>
        <Heading>242.0</Heading>
    </FED>
    <FED Num="97">
        <FeatureCtIdx>936</FeatureCtIdx>
        <OffsetX>7329.690</OffsetX>
        <OffsetY>2985.795</OffsetY>
        <OffsetZ>0.000</OffsetZ>
        <Heading>282.0</Heading>
    </FED>
    <FED Num="98">
        <FeatureCtIdx>892</FeatureCtIdx>
        <OffsetX>-1014.875</OffsetX>
        <OffsetY>2818.418</OffsetY>
        <OffsetZ>0.000</OffsetZ>
        <Heading>64.0</Heading>
    </FED>
    <FED Num="99">
        <FeatureCtIdx>886</FeatureCtIdx>
        <OffsetX>4525.763</OffsetX>
        <OffsetY>1461.828</OffsetY>
        <OffsetZ>0.000</OffsetZ>
        <Heading>242.0</Heading>
    </FED>
    <FED Num="100">
        <FeatureCtIdx>3219</FeatureCtIdx>
        <OffsetX>4145.503</OffsetX>
        <OffsetY>1018.323</OffsetY>
        <OffsetZ>0.000</OffsetZ>
        <Heading>242.0</Heading>
    </FED>
    <FED Num="101">
        <FeatureCtIdx>3218</FeatureCtIdx>
        <OffsetX>4563.509</OffsetX>
        <OffsetY>-420.733</OffsetY>
        <OffsetZ>0.000</OffsetZ>
        <Heading>194.0</Heading>
    </FED>
    <FED Num="102">
        <FeatureCtIdx>3192</FeatureCtIdx>
        <OffsetX>-1619.543</OffsetX>
        <OffsetY>2770.255</OffsetY>
        <OffsetZ>0.000</OffsetZ>
        <Heading>331.0</Heading>
    </FED>
    <FED Num="103">
        <FeatureCtIdx>2601</FeatureCtIdx>
        <OffsetX>3978.577</OffsetX>
        <OffsetY>917.463</OffsetY>
        <OffsetZ>0.000</OffsetZ>
        <Heading>242.0</Heading>
    </FED>
    <FED Num="104">
        <FeatureCtIdx>1790</FeatureCtIdx>
        <OffsetX>3879.789</OffsetX>
        <OffsetY>1078.533</OffsetY>
        <OffsetZ>0.000</OffsetZ>
        <Heading>243.0</Heading>
    </FED>
    <FED Num="105">
        <FeatureCtIdx>3188</FeatureCtIdx>
        <OffsetX>2067.021</OffsetX>
        <OffsetY>231.220</OffsetY>
        <OffsetZ>0.000</OffsetZ>
        <Heading>332.0</Heading>
    </FED>
    <FED Num="106">
        <FeatureCtIdx>3681</FeatureCtIdx>
        <OffsetX>1915.335</OffsetX>
        <OffsetY>216.162</OffsetY>
        <OffsetZ>0.000</OffsetZ>
        <Heading>332.0</Heading>
    </FED>
    <FED Num="107">
        <FeatureCtIdx>1354</FeatureCtIdx>
        <OffsetX>4628.170</OffsetX>
        <OffsetY>656.650</OffsetY>
        <OffsetZ>0.000</OffsetZ>
        <Heading>151.0</Heading>
    </FED>
    <FED Num="108">
        <FeatureCtIdx>2811</FeatureCtIdx>
        <OffsetX>3254.650</OffsetX>
        <OffsetY>-113.109</OffsetY>
        <OffsetZ>0.000</OffsetZ>
        <Heading>268.0</Heading>
    </FED>
    <FED Num="109">
        <FeatureCtIdx>2814</FeatureCtIdx>
        <OffsetX>-1339.508</OffsetX>
        <OffsetY>3069.356</OffsetY>
        <OffsetZ>0.000</OffsetZ>
        <Heading>311.0</Heading>
    </FED>
    <FED Num="110">
        <FeatureCtIdx>2814</FeatureCtIdx>
        <OffsetX>3277.795</OffsetX>
        <OffsetY>-379.016</OffsetY>
        <OffsetZ>0.000</OffsetZ>
        <Heading>345.0</Heading>
    </FED>
    <FED Num="111">
        <FeatureCtIdx>2499</FeatureCtIdx>
        <OffsetX>3127.098</OffsetX>
        <OffsetY>138.547</OffsetY>
        <OffsetZ>0.000</OffsetZ>
        <Heading>152.0</Heading>
    </FED>
    <FED Num="112">
        <FeatureCtIdx>2499</FeatureCtIdx>
        <OffsetX>2969.514</OffsetX>
        <OffsetY>305.620</OffsetY>
        <OffsetZ>0.000</OffsetZ>
        <Heading>152.0</Heading>
    </FED>
    <FED Num="113">
        <FeatureCtIdx>2499</FeatureCtIdx>
        <OffsetX>4958.366</OffsetX>
        <OffsetY>1968.442</OffsetY>
        <OffsetZ>0.000</OffsetZ>
        <Heading>242.0</Heading>
    </FED>
    <FED Num="114">
        <FeatureCtIdx>2499</FeatureCtIdx>
        <OffsetX>5483.800</OffsetX>
        <OffsetY>2573.354</OffsetY>
        <OffsetZ>0.000</OffsetZ>
        <Heading>152.0</Heading>
    </FED>
    <FED Num="115">
        <FeatureCtIdx>2499</FeatureCtIdx>
        <OffsetX>5079.953</OffsetX>
        <OffsetY>2358.669</OffsetY>
        <OffsetZ>0.000</OffsetZ>
        <Heading>152.0</Heading>
    </FED>
    <FED Num="116">
        <FeatureCtIdx>2499</FeatureCtIdx>
        <OffsetX>6455.069</OffsetX>
        <OffsetY>2998.138</OffsetY>
        <OffsetZ>0.000</OffsetZ>
        <Heading>332.0</Heading>
    </FED>
    <FED Num="117">
        <FeatureCtIdx>2499</FeatureCtIdx>
        <OffsetX>8027.693</OffsetX>
        <OffsetY>3189.541</OffsetY>
        <OffsetZ>0.000</OffsetZ>
        <Heading>331.0</Heading>
    </FED>
    <FED Num="118">
        <FeatureCtIdx>2500</FeatureCtIdx>
        <OffsetX>8029.417</OffsetX>
        <OffsetY>3153.455</OffsetY>
        <OffsetZ>0.000</OffsetZ>
        <Heading>331.0</Heading>
    </FED>
    <FED Num="119">
        <FeatureCtIdx>2659</FeatureCtIdx>
        <OffsetX>2558.872</OffsetX>
        <OffsetY>1519.284</OffsetY>
        <OffsetZ>0.000</OffsetZ>
        <Heading>62.0</Heading>
    </FED>
    <FED Num="120">
        <FeatureCtIdx>2989</FeatureCtIdx>
        <OffsetX>6373.024</OffsetX>
        <OffsetY>2619.885</OffsetY>
        <OffsetZ>0.000</OffsetZ>
        <Heading>146.0</Heading>
    </FED>
    <FED Num="121">
        <FeatureCtIdx>2989</FeatureCtIdx>
        <OffsetX>6316.760</OffsetX>
        <OffsetY>2702.599</OffsetY>
        <OffsetZ>0.000</OffsetZ>
        <Heading>146.0</Heading>
    </FED>
    <FED Num="122">
        <FeatureCtIdx>2989</FeatureCtIdx>
        <OffsetX>2435.417</OffsetX>
        <OffsetY>4558.554</OffsetY>
        <OffsetZ>0.000</OffsetZ>
        <Heading>332.0</Heading>
    </FED>
    <FED Num="123">
        <FeatureCtIdx>2989</FeatureCtIdx>
        <OffsetX>2550.511</OffsetX>
        <OffsetY>4620.049</OffsetY>
        <OffsetZ>0.000</OffsetZ>
        <Heading>332.0</Heading>
    </FED>
    <FED Num="124">
        <FeatureCtIdx>3230</FeatureCtIdx>
        <OffsetX>2844.030</OffsetX>
        <OffsetY>317.343</OffsetY>
        <OffsetZ>0.000</OffsetZ>
        <Heading>333.0</Heading>
    </FED>
    <FED Num="125">
        <FeatureCtIdx>3225</FeatureCtIdx>
        <OffsetX>1335.647</OffsetX>
        <OffsetY>3871.232</OffsetY>
        <OffsetZ>0.000</OffsetZ>
        <Heading>242.0</Heading>
    </FED>
    <FED Num="126">
        <FeatureCtIdx>1325</FeatureCtIdx>
        <OffsetX>4622.934</OffsetX>
        <OffsetY>1514.775</OffsetY>
        <OffsetZ>0.000</OffsetZ>
        <Heading>242.0</Heading>
    </FED>
    <FED Num="127">
        <FeatureCtIdx>950</FeatureCtIdx>
        <OffsetX>1890.364</OffsetX>
        <OffsetY>4177.792</OffsetY>
        <OffsetZ>0.000</OffsetZ>
        <Heading>242.0</Heading>
    </FED>
    <FED Num="128">
        <FeatureCtIdx>103</FeatureCtIdx>
        <OffsetX>1509.116</OffsetX>
        <OffsetY>3970.591</OffsetY>
        <OffsetZ>0.000</OffsetZ>
        <Heading>242.0</Heading>
    </FED>
    <FED Num="129">
        <FeatureCtIdx>1325</FeatureCtIdx>
        <OffsetX>-4784.883</OffsetX>
        <OffsetY>-380.595</OffsetY>
        <OffsetZ>0.000</OffsetZ>
        <Heading>95.0</Heading>
    </FED>
    <FED Num="130">
        <FeatureCtIdx>1325</FeatureCtIdx>
        <OffsetX>-4668.107</OffsetX>
        <OffsetY>-390.995</OffsetY>
        <OffsetZ>0.000</OffsetZ>
        <Heading>95.0</Heading>
    </FED>
    <FED Num="131">
        <FeatureCtIdx>1143</FeatureCtIdx>
        <OffsetX>-4487.756</OffsetX>
        <OffsetY>-412.697</OffsetY>
        <OffsetZ>0.000</OffsetZ>
        <Heading>98.0</Heading>
    </FED>
    <FED Num="132">
        <FeatureCtIdx>3198</FeatureCtIdx>
        <OffsetX>-2819.648</OffsetX>
        <OffsetY>1400.727</OffsetY>
        <OffsetZ>0.000</OffsetZ>
        <Heading>62.0</Heading>
    </FED>
    <FED Num="133">
        <FeatureCtIdx>3221</FeatureCtIdx>
        <OffsetX>-867.874</OffsetX>
        <OffsetY>2977.590</OffsetY>
        <OffsetZ>0.000</OffsetZ>
        <Heading>332.0</Heading>
    </FED>
    <FED Num="134">
        <FeatureCtIdx>3221</FeatureCtIdx>
        <OffsetX>-851.775</OffsetX>
        <OffsetY>2899.258</OffsetY>
        <OffsetZ>0.000</OffsetZ>
        <Heading>62.0</Heading>
    </FED>
    <FED Num="135">
        <FeatureCtIdx>3221</FeatureCtIdx>
        <OffsetX>-401.352</OffsetX>
        <OffsetY>3035.035</OffsetY>
        <OffsetZ>0.000</OffsetZ>
        <Heading>62.0</Heading>
    </FED>
    <FED Num="136">
        <FeatureCtIdx>1325</FeatureCtIdx>
        <OffsetX>1480.810</OffsetX>
        <OffsetY>4153.786</OffsetY>
        <OffsetZ>0.000</OffsetZ>
        <Heading>152.0</Heading>
    </FED>
    <FED Num="137">
        <FeatureCtIdx>3225</FeatureCtIdx>
        <OffsetX>3739.921</OffsetX>
        <OffsetY>5099.940</OffsetY>
        <OffsetZ>0.000</OffsetZ>
        <Heading>152.0</Heading>
    </FED>
    <FED Num="138">
        <FeatureCtIdx>3197</FeatureCtIdx>
        <OffsetX>2470.346</OffsetX>
        <OffsetY>-13.929</OffsetY>
        <OffsetZ>0.000</OffsetZ>
        <Heading>151.0</Heading>
    </FED>
    <FED Num="139">
        <FeatureCtIdx>3215</FeatureCtIdx>
        <OffsetX>3898.500</OffsetX>
        <OffsetY>420.083</OffsetY>
        <OffsetZ>0.000</OffsetZ>
        <Heading>241.0</Heading>
    </FED>
    <FED Num="140">
        <FeatureCtIdx>3228</FeatureCtIdx>
        <OffsetX>6851.161</OffsetX>
        <OffsetY>2618.336</OffsetY>
        <OffsetZ>0.000</OffsetZ>
        <Heading>149.0</Heading>
    </FED>
    <FED Num="141">
        <FeatureCtIdx>3197</FeatureCtIdx>
        <OffsetX>-45.869</OffsetX>
        <OffsetY>3273.958</OffsetY>
        <OffsetZ>0.000</OffsetZ>
        <Heading>332.0</Heading>
    </FED>
    <FED Num="142">
        <FeatureCtIdx>869</FeatureCtIdx>
        <OffsetX>1191.901</OffsetX>
        <OffsetY>4049.617</OffsetY>
        <OffsetZ>0.000</OffsetZ>
        <Heading>241.0</Heading>
    </FED>
    <FED Num="143">
        <FeatureCtIdx>869</FeatureCtIdx>
        <OffsetX>1222.712</OffsetX>
        <OffsetY>3993.144</OffsetY>
        <OffsetZ>0.000</OffsetZ>
        <Heading>241.0</Heading>
    </FED>
    <FED Num="144">
        <FeatureCtIdx>3230</FeatureCtIdx>
        <OffsetX>5554.320</OffsetX>
        <OffsetY>2321.810</OffsetY>
        <OffsetZ>0.000</OffsetZ>
        <Heading>244.0</Heading>
    </FED>
    <FED Num="145">
        <FeatureCtIdx>103</FeatureCtIdx>
        <OffsetX>2724.634</OffsetX>
        <OffsetY>4768.640</OffsetY>
        <OffsetZ>0.000</OffsetZ>
        <Heading>62.0</Heading>
    </FED>
    <FED Num="146">
        <FeatureCtIdx>103</FeatureCtIdx>
        <OffsetX>4272.903</OffsetX>
        <OffsetY>105.269</OffsetY>
        <OffsetZ>0.000</OffsetZ>
        <Heading>113.0</Heading>
    </FED>
    <FED Num="147">
        <FeatureCtIdx>103</FeatureCtIdx>
        <OffsetX>3827.804</OffsetX>
        <OffsetY>15.705</OffsetY>
        <OffsetZ>0.000</OffsetZ>
        <Heading>62.0</Heading>
    </FED>
    <FED Num="148">
        <FeatureCtIdx>3230</FeatureCtIdx>
        <OffsetX>5132.242</OffsetX>
        <OffsetY>977.813</OffsetY>
        <OffsetZ>0.000</OffsetZ>
        <Heading>243.0</Heading>
    </FED>
    <FED Num="149">
        <FeatureCtIdx>3197</FeatureCtIdx>
        <OffsetX>4792.622</OffsetX>
        <OffsetY>6333.731</OffsetY>
        <OffsetZ>0.000</OffsetZ>
        <Heading>310.0</Heading>
    </FED>
    <FED Num="150">
        <FeatureCtIdx>3197</FeatureCtIdx>
        <OffsetX>2860.446</OffsetX>
        <OffsetY>605.989</OffsetY>
        <OffsetZ>0.000</OffsetZ>
        <Heading>62.0</Heading>
    </FED>
    <FED Num="151">
        <FeatureCtIdx>3197</FeatureCtIdx>
        <OffsetX>3130.208</OffsetX>
        <OffsetY>751.457</OffsetY>
        <OffsetZ>0.000</OffsetZ>
        <Heading>62.0</Heading>
    </FED>
    <FED Num="152">
        <FeatureCtIdx>103</FeatureCtIdx>
        <OffsetX>4570.273</OffsetX>
        <OffsetY>-1266.135</OffsetY>
        <OffsetZ>0.000</OffsetZ>
        <Heading>277.0</Heading>
    </FED>
</FEDRecords>
