<?xml version="1.0" encoding="utf-8"?>
<FEDRecords>
    <FED Num="0">
        <FeatureCtIdx>1018</FeatureCtIdx>
        <Value>75</Value>
        <OffsetX>-2611.000</OffsetX>
        <OffsetY>3965.000</OffsetY>
        <OffsetZ>0.000</OffsetZ>
        <Heading>33.0</Heading>
    </FED>
    <FED Num="1">
        <FeatureCtIdx>2586</FeatureCtIdx>
        <Value>60</Value>
        <OffsetX>-2638.782</OffsetX>
        <OffsetY>-4694.616</OffsetY>
        <OffsetZ>0.000</OffsetZ>
        <Heading>219.0</Heading>
    </FED>
    <FED Num="2">
        <FeatureCtIdx>2586</FeatureCtIdx>
        <Value>60</Value>
        <OffsetX>-1800.240</OffsetX>
        <OffsetY>-4992.628</OffsetY>
        <OffsetZ>0.000</OffsetZ>
        <Heading>174.0</Heading>
    </FED>
    <FED Num="3">
        <FeatureCtIdx>2586</FeatureCtIdx>
        <Value>60</Value>
        <OffsetX>-1144.945</OffsetX>
        <OffsetY>-4570.713</OffsetY>
        <OffsetZ>0.000</OffsetZ>
        <Heading>178.0</Heading>
    </FED>
    <FED Num="4">
        <FeatureCtIdx>2586</FeatureCtIdx>
        <Value>60</Value>
        <OffsetX>-836.944</OffsetX>
        <OffsetY>-4562.463</OffsetY>
        <OffsetZ>0.000</OffsetZ>
        <Heading>178.0</Heading>
    </FED>
    <FED Num="5">
        <FeatureCtIdx>2586</FeatureCtIdx>
        <Value>60</Value>
        <OffsetX>-935.344</OffsetX>
        <OffsetY>-4564.513</OffsetY>
        <OffsetZ>0.000</OffsetZ>
        <Heading>178.0</Heading>
    </FED>
    <FED Num="6">
        <FeatureCtIdx>2586</FeatureCtIdx>
        <Value>60</Value>
        <OffsetX>-1038.258</OffsetX>
        <OffsetY>-4567.788</OffsetY>
        <OffsetZ>0.000</OffsetZ>
        <Heading>178.0</Heading>
    </FED>
    <FED Num="7">
        <FeatureCtIdx>2586</FeatureCtIdx>
        <Value>60</Value>
        <OffsetX>-828.543</OffsetX>
        <OffsetY>-4722.875</OffsetY>
        <OffsetZ>0.000</OffsetZ>
        <Heading>178.0</Heading>
    </FED>
    <FED Num="8">
        <FeatureCtIdx>2586</FeatureCtIdx>
        <Value>60</Value>
        <OffsetX>-926.943</OffsetX>
        <OffsetY>-4724.925</OffsetY>
        <OffsetZ>0.000</OffsetZ>
        <Heading>178.0</Heading>
    </FED>
    <FED Num="9">
        <FeatureCtIdx>2586</FeatureCtIdx>
        <Value>60</Value>
        <OffsetX>-1029.855</OffsetX>
        <OffsetY>-4728.198</OffsetY>
        <OffsetZ>0.000</OffsetZ>
        <Heading>178.0</Heading>
    </FED>
    <FED Num="10">
        <FeatureCtIdx>2586</FeatureCtIdx>
        <Value>60</Value>
        <OffsetX>-1136.606</OffsetX>
        <OffsetY>-4735.871</OffsetY>
        <OffsetZ>0.000</OffsetZ>
        <Heading>178.0</Heading>
    </FED>
    <FED Num="11">
        <FeatureCtIdx>2586</FeatureCtIdx>
        <Value>60</Value>
        <OffsetX>-821.034</OffsetX>
        <OffsetY>-4879.831</OffsetY>
        <OffsetZ>0.000</OffsetZ>
        <Heading>178.0</Heading>
    </FED>
    <FED Num="12">
        <FeatureCtIdx>2586</FeatureCtIdx>
        <Value>60</Value>
        <OffsetX>-924.934</OffsetX>
        <OffsetY>-4884.630</OffsetY>
        <OffsetZ>0.000</OffsetZ>
        <Heading>178.0</Heading>
    </FED>
    <FED Num="13">
        <FeatureCtIdx>2586</FeatureCtIdx>
        <Value>60</Value>
        <OffsetX>-1129.097</OffsetX>
        <OffsetY>-4890.078</OffsetY>
        <OffsetZ>0.000</OffsetZ>
        <Heading>178.0</Heading>
    </FED>
    <FED Num="14">
        <FeatureCtIdx>2586</FeatureCtIdx>
        <Value>60</Value>
        <OffsetX>-1027.847</OffsetX>
        <OffsetY>-4887.904</OffsetY>
        <OffsetZ>0.000</OffsetZ>
        <Heading>178.0</Heading>
    </FED>
    <FED Num="15">
        <FeatureCtIdx>2586</FeatureCtIdx>
        <Value>60</Value>
        <OffsetX>-795.205</OffsetX>
        <OffsetY>-5074.361</OffsetY>
        <OffsetZ>0.000</OffsetZ>
        <Heading>178.0</Heading>
    </FED>
    <FED Num="16">
        <FeatureCtIdx>2586</FeatureCtIdx>
        <Value>60</Value>
        <OffsetX>-900.417</OffsetX>
        <OffsetY>-5078.873</OffsetY>
        <OffsetZ>0.000</OffsetZ>
        <Heading>358.0</Heading>
    </FED>
    <FED Num="17">
        <FeatureCtIdx>2586</FeatureCtIdx>
        <Value>60</Value>
        <OffsetX>-1109.668</OffsetX>
        <OffsetY>-5084.322</OffsetY>
        <OffsetZ>0.000</OffsetZ>
        <Heading>178.0</Heading>
    </FED>
    <FED Num="18">
        <FeatureCtIdx>2586</FeatureCtIdx>
        <Value>60</Value>
        <OffsetX>-1002.179</OffsetX>
        <OffsetY>-5082.147</OffsetY>
        <OffsetZ>0.000</OffsetZ>
        <Heading>178.0</Heading>
    </FED>
    <FED Num="19">
        <FeatureCtIdx>2586</FeatureCtIdx>
        <Value>60</Value>
        <OffsetX>-791.612</OffsetX>
        <OffsetY>-5272.524</OffsetY>
        <OffsetZ>0.000</OffsetZ>
        <Heading>178.0</Heading>
    </FED>
    <FED Num="20">
        <FeatureCtIdx>2586</FeatureCtIdx>
        <Value>60</Value>
        <OffsetX>-896.824</OffsetX>
        <OffsetY>-5277.036</OffsetY>
        <OffsetZ>0.000</OffsetZ>
        <Heading>178.0</Heading>
    </FED>
    <FED Num="21">
        <FeatureCtIdx>2586</FeatureCtIdx>
        <Value>60</Value>
        <OffsetX>-1103.325</OffsetX>
        <OffsetY>-5282.485</OffsetY>
        <OffsetZ>0.000</OffsetZ>
        <Heading>178.0</Heading>
    </FED>
    <FED Num="22">
        <FeatureCtIdx>2586</FeatureCtIdx>
        <Value>60</Value>
        <OffsetX>-998.588</OffsetX>
        <OffsetY>-5280.310</OffsetY>
        <OffsetZ>0.000</OffsetZ>
        <Heading>178.0</Heading>
    </FED>
    <FED Num="23">
        <FeatureCtIdx>2600</FeatureCtIdx>
        <OffsetX>-1256.521</OffsetX>
        <OffsetY>-5762.122</OffsetY>
        <OffsetZ>0.000</OffsetZ>
        <Heading>92.0</Heading>
    </FED>
    <FED Num="24">
        <FeatureCtIdx>2600</FeatureCtIdx>
        <OffsetX>-684.678</OffsetX>
        <OffsetY>-5710.546</OffsetY>
        <OffsetZ>0.000</OffsetZ>
        <Heading>342.0</Heading>
    </FED>
    <FED Num="25">
        <FeatureCtIdx>2599</FeatureCtIdx>
        <Value>60</Value>
        <OffsetX>-393.029</OffsetX>
        <OffsetY>-5695.089</OffsetY>
        <OffsetZ>0.000</OffsetZ>
        <Heading>356.0</Heading>
    </FED>
    <FED Num="26">
        <FeatureCtIdx>2599</FeatureCtIdx>
        <Value>60</Value>
        <OffsetX>-516.154</OffsetX>
        <OffsetY>-5704.936</OffsetY>
        <OffsetZ>0.000</OffsetZ>
        <Heading>356.0</Heading>
    </FED>
    <FED Num="27">
        <FeatureCtIdx>2599</FeatureCtIdx>
        <Value>60</Value>
        <OffsetX>-855.979</OffsetX>
        <OffsetY>-5719.710</OffsetY>
        <OffsetZ>0.000</OffsetZ>
        <Heading>356.0</Heading>
    </FED>
    <FED Num="28">
        <FeatureCtIdx>2599</FeatureCtIdx>
        <Value>60</Value>
        <OffsetX>-979.104</OffsetX>
        <OffsetY>-5729.561</OffsetY>
        <OffsetZ>0.000</OffsetZ>
        <Heading>356.0</Heading>
    </FED>
    <FED Num="29">
        <FeatureCtIdx>2599</FeatureCtIdx>
        <Value>60</Value>
        <OffsetX>-181.979</OffsetX>
        <OffsetY>-5944.298</OffsetY>
        <OffsetZ>0.000</OffsetZ>
        <Heading>356.0</Heading>
    </FED>
    <FED Num="30">
        <FeatureCtIdx>2599</FeatureCtIdx>
        <Value>60</Value>
        <OffsetX>-545.036</OffsetX>
        <OffsetY>-5482.383</OffsetY>
        <OffsetZ>0.000</OffsetZ>
        <Heading>356.0</Heading>
    </FED>
    <FED Num="31">
        <FeatureCtIdx>2599</FeatureCtIdx>
        <Value>60</Value>
        <OffsetX>-668.162</OffsetX>
        <OffsetY>-5492.233</OffsetY>
        <OffsetZ>0.000</OffsetZ>
        <Heading>356.0</Heading>
    </FED>
    <FED Num="32">
        <FeatureCtIdx>2599</FeatureCtIdx>
        <Value>60</Value>
        <OffsetX>-788.825</OffsetX>
        <OffsetY>-5497.159</OffsetY>
        <OffsetZ>0.000</OffsetZ>
        <Heading>356.0</Heading>
    </FED>
    <FED Num="33">
        <FeatureCtIdx>2599</FeatureCtIdx>
        <Value>60</Value>
        <OffsetX>-1015.376</OffsetX>
        <OffsetY>-5511.937</OffsetY>
        <OffsetZ>0.000</OffsetZ>
        <Heading>356.0</Heading>
    </FED>
    <FED Num="34">
        <FeatureCtIdx>2599</FeatureCtIdx>
        <Value>60</Value>
        <OffsetX>-1136.040</OffsetX>
        <OffsetY>-5521.786</OffsetY>
        <OffsetZ>0.000</OffsetZ>
        <Heading>356.0</Heading>
    </FED>
    <FED Num="35">
        <FeatureCtIdx>2599</FeatureCtIdx>
        <Value>60</Value>
        <OffsetX>-1261.627</OffsetX>
        <OffsetY>-5531.634</OffsetY>
        <OffsetZ>0.000</OffsetZ>
        <Heading>356.0</Heading>
    </FED>
    <FED Num="36">
        <FeatureCtIdx>2599</FeatureCtIdx>
        <Value>60</Value>
        <OffsetX>-305.104</OffsetX>
        <OffsetY>-5954.147</OffsetY>
        <OffsetZ>0.000</OffsetZ>
        <Heading>356.0</Heading>
    </FED>
    <FED Num="37">
        <FeatureCtIdx>2599</FeatureCtIdx>
        <Value>60</Value>
        <OffsetX>-425.766</OffsetX>
        <OffsetY>-5963.997</OffsetY>
        <OffsetZ>0.000</OffsetZ>
        <Heading>356.0</Heading>
    </FED>
    <FED Num="38">
        <FeatureCtIdx>2599</FeatureCtIdx>
        <Value>60</Value>
        <OffsetX>-548.892</OffsetX>
        <OffsetY>-5971.385</OffsetY>
        <OffsetZ>0.000</OffsetZ>
        <Heading>356.0</Heading>
    </FED>
    <FED Num="39">
        <FeatureCtIdx>2599</FeatureCtIdx>
        <Value>60</Value>
        <OffsetX>-669.554</OffsetX>
        <OffsetY>-5978.772</OffsetY>
        <OffsetZ>0.000</OffsetZ>
        <Heading>356.0</Heading>
    </FED>
    <FED Num="40">
        <FeatureCtIdx>2599</FeatureCtIdx>
        <Value>60</Value>
        <OffsetX>-795.142</OffsetX>
        <OffsetY>-5988.622</OffsetY>
        <OffsetZ>0.000</OffsetZ>
        <Heading>356.0</Heading>
    </FED>
    <FED Num="41">
        <FeatureCtIdx>2599</FeatureCtIdx>
        <Value>60</Value>
        <OffsetX>-918.267</OffsetX>
        <OffsetY>-5998.472</OffsetY>
        <OffsetZ>0.000</OffsetZ>
        <Heading>356.0</Heading>
    </FED>
    <FED Num="42">
        <FeatureCtIdx>2599</FeatureCtIdx>
        <Value>60</Value>
        <OffsetX>-1038.930</OffsetX>
        <OffsetY>-6008.321</OffsetY>
        <OffsetZ>0.000</OffsetZ>
        <Heading>356.0</Heading>
    </FED>
    <FED Num="43">
        <FeatureCtIdx>2599</FeatureCtIdx>
        <Value>60</Value>
        <OffsetX>-1162.055</OffsetX>
        <OffsetY>-6015.707</OffsetY>
        <OffsetZ>0.000</OffsetZ>
        <Heading>356.0</Heading>
    </FED>
    <FED Num="44">
        <FeatureCtIdx>2599</FeatureCtIdx>
        <Value>60</Value>
        <OffsetX>-1102.229</OffsetX>
        <OffsetY>-5739.412</OffsetY>
        <OffsetZ>0.000</OffsetZ>
        <Heading>356.0</Heading>
    </FED>
    <FED Num="45">
        <FeatureCtIdx>2585</FeatureCtIdx>
        <Value>60</Value>
        <OffsetX>-1286.255</OffsetX>
        <OffsetY>-4191.896</OffsetY>
        <OffsetZ>0.000</OffsetZ>
        <Heading>180.0</Heading>
    </FED>
    <FED Num="46">
        <FeatureCtIdx>2585</FeatureCtIdx>
        <Value>60</Value>
        <OffsetX>-1126.636</OffsetX>
        <OffsetY>-3884.061</OffsetY>
        <OffsetZ>0.000</OffsetZ>
        <Heading>180.0</Heading>
    </FED>
    <FED Num="47">
        <FeatureCtIdx>2585</FeatureCtIdx>
        <Value>60</Value>
        <OffsetX>-1386.863</OffsetX>
        <OffsetY>-3937.513</OffsetY>
        <OffsetZ>0.000</OffsetZ>
        <Heading>270.0</Heading>
    </FED>
    <FED Num="48">
        <FeatureCtIdx>2585</FeatureCtIdx>
        <Value>60</Value>
        <OffsetX>-2646.431</OffsetX>
        <OffsetY>-4236.319</OffsetY>
        <OffsetZ>0.000</OffsetZ>
        <Heading>180.0</Heading>
    </FED>
    <FED Num="49">
        <FeatureCtIdx>2585</FeatureCtIdx>
        <Value>60</Value>
        <OffsetX>-2383.163</OffsetX>
        <OffsetY>-4229.540</OffsetY>
        <OffsetZ>0.000</OffsetZ>
        <Heading>180.0</Heading>
    </FED>
    <FED Num="50">
        <FeatureCtIdx>2585</FeatureCtIdx>
        <Value>60</Value>
        <OffsetX>-2401.462</OffsetX>
        <OffsetY>-3896.126</OffsetY>
        <OffsetZ>0.000</OffsetZ>
        <Heading>179.0</Heading>
    </FED>
    <FED Num="51">
        <FeatureCtIdx>2585</FeatureCtIdx>
        <Value>60</Value>
        <OffsetX>-2087.980</OffsetX>
        <OffsetY>-4210.330</OffsetY>
        <OffsetZ>0.000</OffsetZ>
        <Heading>0.0</Heading>
    </FED>
    <FED Num="52">
        <FeatureCtIdx>2585</FeatureCtIdx>
        <Value>60</Value>
        <OffsetX>-1837.242</OffsetX>
        <OffsetY>-4204.529</OffsetY>
        <OffsetZ>0.000</OffsetZ>
        <Heading>0.0</Heading>
    </FED>
    <FED Num="53">
        <FeatureCtIdx>2585</FeatureCtIdx>
        <Value>60</Value>
        <OffsetX>-1557.173</OffsetX>
        <OffsetY>-4193.513</OffsetY>
        <OffsetZ>0.000</OffsetZ>
        <Heading>0.0</Heading>
    </FED>
    <FED Num="54">
        <FeatureCtIdx>2585</FeatureCtIdx>
        <Value>60</Value>
        <OffsetX>-1717.896</OffsetX>
        <OffsetY>-3833.179</OffsetY>
        <OffsetZ>0.000</OffsetZ>
        <Heading>0.0</Heading>
    </FED>
    <FED Num="55">
        <FeatureCtIdx>2585</FeatureCtIdx>
        <Value>60</Value>
        <OffsetX>-1975.825</OffsetX>
        <OffsetY>-3872.654</OffsetY>
        <OffsetZ>0.000</OffsetZ>
        <Heading>359.0</Heading>
    </FED>
    <FED Num="56">
        <FeatureCtIdx>2585</FeatureCtIdx>
        <Value>60</Value>
        <OffsetX>-2702.275</OffsetX>
        <OffsetY>-3866.954</OffsetY>
        <OffsetZ>0.000</OffsetZ>
        <Heading>0.0</Heading>
    </FED>
    <FED Num="57">
        <FeatureCtIdx>2496</FeatureCtIdx>
        <OffsetX>-1067.099</OffsetX>
        <OffsetY>-3881.682</OffsetY>
        <OffsetZ>0.000</OffsetZ>
        <Heading>0.0</Heading>
    </FED>
    <FED Num="58">
        <FeatureCtIdx>2499</FeatureCtIdx>
        <OffsetX>-624.799</OffsetX>
        <OffsetY>-3874.634</OffsetY>
        <OffsetZ>0.000</OffsetZ>
        <Heading>9.0</Heading>
    </FED>
    <FED Num="59">
        <FeatureCtIdx>2797</FeatureCtIdx>
        <OffsetX>-606.917</OffsetX>
        <OffsetY>-3762.808</OffsetY>
        <OffsetZ>0.000</OffsetZ>
        <Heading>99.0</Heading>
    </FED>
    <FED Num="60">
        <FeatureCtIdx>2797</FeatureCtIdx>
        <OffsetX>-674.559</OffsetX>
        <OffsetY>-3751.918</OffsetY>
        <OffsetZ>0.000</OffsetZ>
        <Heading>99.0</Heading>
    </FED>
    <FED Num="61">
        <FeatureCtIdx>2797</FeatureCtIdx>
        <OffsetX>-473.222</OffsetX>
        <OffsetY>-3783.984</OffsetY>
        <OffsetZ>0.000</OffsetZ>
        <Heading>99.0</Heading>
    </FED>
    <FED Num="62">
        <FeatureCtIdx>2797</FeatureCtIdx>
        <OffsetX>-540.863</OffsetX>
        <OffsetY>-3773.094</OffsetY>
        <OffsetZ>0.000</OffsetZ>
        <Heading>99.0</Heading>
    </FED>
    <FED Num="63">
        <FeatureCtIdx>2797</FeatureCtIdx>
        <OffsetX>-333.882</OffsetX>
        <OffsetY>-3807.559</OffsetY>
        <OffsetZ>0.000</OffsetZ>
        <Heading>99.0</Heading>
    </FED>
    <FED Num="64">
        <FeatureCtIdx>2797</FeatureCtIdx>
        <OffsetX>-401.523</OffsetX>
        <OffsetY>-3796.668</OffsetY>
        <OffsetZ>0.000</OffsetZ>
        <Heading>99.0</Heading>
    </FED>
    <FED Num="65">
        <FeatureCtIdx>2797</FeatureCtIdx>
        <OffsetX>-804.207</OffsetX>
        <OffsetY>-3726.884</OffsetY>
        <OffsetZ>0.000</OffsetZ>
        <Heading>99.0</Heading>
    </FED>
    <FED Num="66">
        <FeatureCtIdx>2797</FeatureCtIdx>
        <OffsetX>-871.849</OffsetX>
        <OffsetY>-3715.994</OffsetY>
        <OffsetZ>0.000</OffsetZ>
        <Heading>99.0</Heading>
    </FED>
    <FED Num="67">
        <FeatureCtIdx>2811</FeatureCtIdx>
        <OffsetX>-2895.265</OffsetX>
        <OffsetY>-3495.324</OffsetY>
        <OffsetZ>0.000</OffsetZ>
        <Heading>0.0</Heading>
    </FED>
    <FED Num="68">
        <FeatureCtIdx>2814</FeatureCtIdx>
        <OffsetX>-2448.750</OffsetX>
        <OffsetY>-3141.500</OffsetY>
        <OffsetZ>0.000</OffsetZ>
        <Heading>225.0</Heading>
    </FED>
    <FED Num="69">
        <FeatureCtIdx>2814</FeatureCtIdx>
        <OffsetX>-2182.500</OffsetX>
        <OffsetY>-2890.250</OffsetY>
        <OffsetZ>0.000</OffsetZ>
        <Heading>273.0</Heading>
    </FED>
    <FED Num="70">
        <FeatureCtIdx>2814</FeatureCtIdx>
        <OffsetX>-1800.000</OffsetX>
        <OffsetY>-3115.250</OffsetY>
        <OffsetZ>0.000</OffsetZ>
        <Heading>0.0</Heading>
    </FED>
    <FED Num="71">
        <FeatureCtIdx>2830</FeatureCtIdx>
        <OffsetX>-2571.750</OffsetX>
        <OffsetY>-2878.500</OffsetY>
        <OffsetZ>0.000</OffsetZ>
        <Heading>0.0</Heading>
    </FED>
    <FED Num="72">
        <FeatureCtIdx>2811</FeatureCtIdx>
        <OffsetX>-2145.000</OffsetX>
        <OffsetY>-3164.250</OffsetY>
        <OffsetZ>0.000</OffsetZ>
        <Heading>0.0</Heading>
    </FED>
    <FED Num="73">
        <FeatureCtIdx>2795</FeatureCtIdx>
        <OffsetX>-1049.757</OffsetX>
        <OffsetY>-6209.114</OffsetY>
        <OffsetZ>0.000</OffsetZ>
        <Heading>122.0</Heading>
    </FED>
    <FED Num="74">
        <FeatureCtIdx>2795</FeatureCtIdx>
        <OffsetX>-600.543</OffsetX>
        <OffsetY>-6176.432</OffsetY>
        <OffsetZ>0.000</OffsetZ>
        <Heading>229.0</Heading>
    </FED>
    <FED Num="75">
        <FeatureCtIdx>2795</FeatureCtIdx>
        <OffsetX>-589.497</OffsetX>
        <OffsetY>-6402.183</OffsetY>
        <OffsetZ>0.000</OffsetZ>
        <Heading>55.0</Heading>
    </FED>
    <FED Num="76">
        <FeatureCtIdx>2683</FeatureCtIdx>
        <OffsetX>-1525.132</OffsetX>
        <OffsetY>-4034.982</OffsetY>
        <OffsetZ>0.000</OffsetZ>
        <Heading>1.0</Heading>
    </FED>
    <FED Num="77">
        <FeatureCtIdx>2683</FeatureCtIdx>
        <OffsetX>-1785.446</OffsetX>
        <OffsetY>-4031.423</OffsetY>
        <OffsetZ>0.000</OffsetZ>
        <Heading>1.0</Heading>
    </FED>
    <FED Num="78">
        <FeatureCtIdx>2683</FeatureCtIdx>
        <OffsetX>-2045.760</OffsetX>
        <OffsetY>-4027.863</OffsetY>
        <OffsetZ>0.000</OffsetZ>
        <Heading>1.0</Heading>
    </FED>
    <FED Num="79">
        <FeatureCtIdx>2683</FeatureCtIdx>
        <OffsetX>-2306.073</OffsetX>
        <OffsetY>-4024.304</OffsetY>
        <OffsetZ>0.000</OffsetZ>
        <Heading>1.0</Heading>
    </FED>
    <FED Num="80">
        <FeatureCtIdx>2683</FeatureCtIdx>
        <OffsetX>-2566.385</OffsetX>
        <OffsetY>-4020.745</OffsetY>
        <OffsetZ>0.000</OffsetZ>
        <Heading>1.0</Heading>
    </FED>
    <FED Num="81">
        <FeatureCtIdx>2684</FeatureCtIdx>
        <OffsetX>-410.920</OffsetX>
        <OffsetY>-3855.141</OffsetY>
        <OffsetZ>0.000</OffsetZ>
        <Heading>9.0</Heading>
    </FED>
    <FED Num="82">
        <FeatureCtIdx>2684</FeatureCtIdx>
        <OffsetX>-683.831</OffsetX>
        <OffsetY>-3811.099</OffsetY>
        <OffsetZ>0.000</OffsetZ>
        <Heading>9.0</Heading>
    </FED>
    <FED Num="83">
        <FeatureCtIdx>2684</FeatureCtIdx>
        <OffsetX>-954.979</OffsetX>
        <OffsetY>-3751.858</OffsetY>
        <OffsetZ>0.000</OffsetZ>
        <Heading>9.0</Heading>
    </FED>
    <FED Num="84">
        <FeatureCtIdx>2847</FeatureCtIdx>
        <OffsetX>-2872.829</OffsetX>
        <OffsetY>-2641.001</OffsetY>
        <OffsetZ>0.000</OffsetZ>
        <Heading>210.0</Heading>
    </FED>
    <FED Num="85">
        <FeatureCtIdx>2847</FeatureCtIdx>
        <OffsetX>-2753.928</OffsetX>
        <OffsetY>-2490.357</OffsetY>
        <OffsetZ>0.000</OffsetZ>
        <Heading>30.0</Heading>
    </FED>
    <FED Num="86">
        <FeatureCtIdx>2847</FeatureCtIdx>
        <OffsetX>-2980.284</OffsetX>
        <OffsetY>-2409.450</OffsetY>
        <OffsetZ>0.000</OffsetZ>
        <Heading>210.0</Heading>
    </FED>
    <FED Num="87">
        <FeatureCtIdx>2847</FeatureCtIdx>
        <OffsetX>-2881.364</OffsetX>
        <OffsetY>-2226.540</OffsetY>
        <OffsetZ>0.000</OffsetZ>
        <Heading>30.0</Heading>
    </FED>
    <FED Num="88">
        <FeatureCtIdx>2847</FeatureCtIdx>
        <OffsetX>-2425.800</OffsetX>
        <OffsetY>-2646.704</OffsetY>
        <OffsetZ>0.000</OffsetZ>
        <Heading>335.0</Heading>
    </FED>
    <FED Num="89">
        <FeatureCtIdx>2847</FeatureCtIdx>
        <OffsetX>-2126.929</OffsetX>
        <OffsetY>-2494.134</OffsetY>
        <OffsetZ>0.000</OffsetZ>
        <Heading>335.0</Heading>
    </FED>
    <FED Num="90">
        <FeatureCtIdx>2847</FeatureCtIdx>
        <OffsetX>-3271.405</OffsetX>
        <OffsetY>-4058.245</OffsetY>
        <OffsetZ>0.000</OffsetZ>
        <Heading>271.0</Heading>
    </FED>
    <FED Num="91">
        <FeatureCtIdx>2847</FeatureCtIdx>
        <OffsetX>-3260.156</OffsetX>
        <OffsetY>-4264.917</OffsetY>
        <OffsetZ>0.000</OffsetZ>
        <Heading>318.0</Heading>
    </FED>
    <FED Num="92">
        <FeatureCtIdx>2847</FeatureCtIdx>
        <OffsetX>-3776.493</OffsetX>
        <OffsetY>-8548.375</OffsetY>
        <OffsetZ>0.000</OffsetZ>
        <Heading>302.0</Heading>
    </FED>
    <FED Num="93">
        <FeatureCtIdx>2847</FeatureCtIdx>
        <OffsetX>-3435.520</OffsetX>
        <OffsetY>-8410.740</OffsetY>
        <OffsetZ>0.000</OffsetZ>
        <Heading>312.0</Heading>
    </FED>
    <FED Num="94">
        <FeatureCtIdx>2847</FeatureCtIdx>
        <OffsetX>-3164.917</OffsetX>
        <OffsetY>-7916.562</OffsetY>
        <OffsetZ>0.000</OffsetZ>
        <Heading>280.0</Heading>
    </FED>
    <FED Num="95">
        <FeatureCtIdx>2847</FeatureCtIdx>
        <OffsetX>-3361.583</OffsetX>
        <OffsetY>-7534.639</OffsetY>
        <OffsetZ>0.000</OffsetZ>
        <Heading>121.0</Heading>
    </FED>
    <FED Num="96">
        <FeatureCtIdx>2847</FeatureCtIdx>
        <OffsetX>-3034.146</OffsetX>
        <OffsetY>-7372.271</OffsetY>
        <OffsetZ>0.000</OffsetZ>
        <Heading>339.0</Heading>
    </FED>
    <FED Num="97">
        <FeatureCtIdx>2847</FeatureCtIdx>
        <OffsetX>-2964.030</OffsetX>
        <OffsetY>-7074.200</OffsetY>
        <OffsetZ>0.000</OffsetZ>
        <Heading>272.0</Heading>
    </FED>
    <FED Num="98">
        <FeatureCtIdx>2847</FeatureCtIdx>
        <OffsetX>-3016.168</OffsetX>
        <OffsetY>-6752.172</OffsetY>
        <OffsetZ>0.000</OffsetZ>
        <Heading>254.0</Heading>
    </FED>
    <FED Num="99">
        <FeatureCtIdx>2847</FeatureCtIdx>
        <OffsetX>-3068.546</OffsetX>
        <OffsetY>-6420.708</OffsetY>
        <OffsetZ>0.000</OffsetZ>
        <Heading>269.0</Heading>
    </FED>
    <FED Num="100">
        <FeatureCtIdx>2847</FeatureCtIdx>
        <OffsetX>-3092.795</OffsetX>
        <OffsetY>-6117.935</OffsetY>
        <OffsetZ>0.000</OffsetZ>
        <Heading>268.0</Heading>
    </FED>
    <FED Num="101">
        <FeatureCtIdx>2847</FeatureCtIdx>
        <OffsetX>-3117.128</OffsetX>
        <OffsetY>-5828.312</OffsetY>
        <OffsetZ>0.000</OffsetZ>
        <Heading>272.0</Heading>
    </FED>
    <FED Num="102">
        <FeatureCtIdx>2847</FeatureCtIdx>
        <OffsetX>-3160.211</OffsetX>
        <OffsetY>-5485.602</OffsetY>
        <OffsetZ>0.000</OffsetZ>
        <Heading>306.0</Heading>
    </FED>
    <FED Num="103">
        <FeatureCtIdx>2847</FeatureCtIdx>
        <OffsetX>-3163.719</OffsetX>
        <OffsetY>-5249.457</OffsetY>
        <OffsetZ>0.000</OffsetZ>
        <Heading>268.0</Heading>
    </FED>
    <FED Num="104">
        <FeatureCtIdx>2847</FeatureCtIdx>
        <OffsetX>-3186.446</OffsetX>
        <OffsetY>-5006.273</OffsetY>
        <OffsetZ>0.000</OffsetZ>
        <Heading>259.0</Heading>
    </FED>
    <FED Num="105">
        <FeatureCtIdx>2847</FeatureCtIdx>
        <OffsetX>-3454.182</OffsetX>
        <OffsetY>-4758.648</OffsetY>
        <OffsetZ>0.000</OffsetZ>
        <Heading>179.0</Heading>
    </FED>
    <FED Num="106">
        <FeatureCtIdx>2847</FeatureCtIdx>
        <OffsetX>-3598.495</OffsetX>
        <OffsetY>-4685.021</OffsetY>
        <OffsetZ>0.000</OffsetZ>
        <Heading>92.0</Heading>
    </FED>
    <FED Num="107">
        <FeatureCtIdx>2847</FeatureCtIdx>
        <OffsetX>-3471.246</OffsetX>
        <OffsetY>-4508.160</OffsetY>
        <OffsetZ>0.000</OffsetZ>
        <Heading>177.0</Heading>
    </FED>
    <FED Num="108">
        <FeatureCtIdx>2847</FeatureCtIdx>
        <OffsetX>-3489.007</OffsetX>
        <OffsetY>-4137.860</OffsetY>
        <OffsetZ>0.000</OffsetZ>
        <Heading>88.0</Heading>
    </FED>
    <FED Num="109">
        <FeatureCtIdx>2847</FeatureCtIdx>
        <OffsetX>-3486.161</OffsetX>
        <OffsetY>-4280.475</OffsetY>
        <OffsetZ>0.000</OffsetZ>
        <Heading>50.0</Heading>
    </FED>
    <FED Num="110">
        <FeatureCtIdx>2847</FeatureCtIdx>
        <OffsetX>-3514.497</OffsetX>
        <OffsetY>-3956.341</OffsetY>
        <OffsetZ>0.000</OffsetZ>
        <Heading>40.0</Heading>
    </FED>
    <FED Num="111">
        <FeatureCtIdx>2847</FeatureCtIdx>
        <OffsetX>-3287.204</OffsetX>
        <OffsetY>-3657.521</OffsetY>
        <OffsetZ>0.000</OffsetZ>
        <Heading>266.0</Heading>
    </FED>
    <FED Num="112">
        <FeatureCtIdx>2847</FeatureCtIdx>
        <OffsetX>-3311.635</OffsetX>
        <OffsetY>-3234.263</OffsetY>
        <OffsetZ>0.000</OffsetZ>
        <Heading>266.0</Heading>
    </FED>
    <FED Num="113">
        <FeatureCtIdx>2847</FeatureCtIdx>
        <OffsetX>-3324.868</OffsetX>
        <OffsetY>-2784.605</OffsetY>
        <OffsetZ>0.000</OffsetZ>
        <Heading>262.0</Heading>
    </FED>
    <FED Num="114">
        <FeatureCtIdx>2847</FeatureCtIdx>
        <OffsetX>-3346.724</OffsetX>
        <OffsetY>-2359.030</OffsetY>
        <OffsetZ>0.000</OffsetZ>
        <Heading>270.0</Heading>
    </FED>
    <FED Num="115">
        <FeatureCtIdx>2847</FeatureCtIdx>
        <OffsetX>-784.863</OffsetX>
        <OffsetY>-4505.014</OffsetY>
        <OffsetZ>0.000</OffsetZ>
        <Heading>178.0</Heading>
    </FED>
    <FED Num="116">
        <FeatureCtIdx>2847</FeatureCtIdx>
        <OffsetX>-889.862</OffsetX>
        <OffsetY>-4508.451</OffsetY>
        <OffsetZ>0.000</OffsetZ>
        <Heading>178.0</Heading>
    </FED>
    <FED Num="117">
        <FeatureCtIdx>2847</FeatureCtIdx>
        <OffsetX>-993.299</OffsetX>
        <OffsetY>-4511.889</OffsetY>
        <OffsetZ>0.000</OffsetZ>
        <Heading>178.0</Heading>
    </FED>
    <FED Num="118">
        <FeatureCtIdx>2847</FeatureCtIdx>
        <OffsetX>-1097.362</OffsetX>
        <OffsetY>-4515.951</OffsetY>
        <OffsetZ>0.000</OffsetZ>
        <Heading>178.0</Heading>
    </FED>
    <FED Num="119">
        <FeatureCtIdx>2847</FeatureCtIdx>
        <OffsetX>-1201.737</OffsetX>
        <OffsetY>-4517.826</OffsetY>
        <OffsetZ>0.000</OffsetZ>
        <Heading>178.0</Heading>
    </FED>
    <FED Num="120">
        <FeatureCtIdx>2847</FeatureCtIdx>
        <OffsetX>-772.249</OffsetX>
        <OffsetY>-4673.297</OffsetY>
        <OffsetZ>0.000</OffsetZ>
        <Heading>178.0</Heading>
    </FED>
    <FED Num="121">
        <FeatureCtIdx>2847</FeatureCtIdx>
        <OffsetX>-877.249</OffsetX>
        <OffsetY>-4676.735</OffsetY>
        <OffsetZ>0.000</OffsetZ>
        <Heading>178.0</Heading>
    </FED>
    <FED Num="122">
        <FeatureCtIdx>2847</FeatureCtIdx>
        <OffsetX>-980.687</OffsetX>
        <OffsetY>-4680.172</OffsetY>
        <OffsetZ>0.000</OffsetZ>
        <Heading>178.0</Heading>
    </FED>
    <FED Num="123">
        <FeatureCtIdx>2847</FeatureCtIdx>
        <OffsetX>-1084.749</OffsetX>
        <OffsetY>-4684.235</OffsetY>
        <OffsetZ>0.000</OffsetZ>
        <Heading>178.0</Heading>
    </FED>
    <FED Num="124">
        <FeatureCtIdx>2847</FeatureCtIdx>
        <OffsetX>-1189.125</OffsetX>
        <OffsetY>-4686.110</OffsetY>
        <OffsetZ>0.000</OffsetZ>
        <Heading>178.0</Heading>
    </FED>
    <FED Num="125">
        <FeatureCtIdx>2847</FeatureCtIdx>
        <OffsetX>-769.918</OffsetX>
        <OffsetY>-4833.943</OffsetY>
        <OffsetZ>0.000</OffsetZ>
        <Heading>178.0</Heading>
    </FED>
    <FED Num="126">
        <FeatureCtIdx>2847</FeatureCtIdx>
        <OffsetX>-874.918</OffsetX>
        <OffsetY>-4837.380</OffsetY>
        <OffsetZ>0.000</OffsetZ>
        <Heading>178.0</Heading>
    </FED>
    <FED Num="127">
        <FeatureCtIdx>2847</FeatureCtIdx>
        <OffsetX>-978.355</OffsetX>
        <OffsetY>-4840.818</OffsetY>
        <OffsetZ>0.000</OffsetZ>
        <Heading>178.0</Heading>
    </FED>
    <FED Num="128">
        <FeatureCtIdx>2847</FeatureCtIdx>
        <OffsetX>-1082.417</OffsetX>
        <OffsetY>-4844.880</OffsetY>
        <OffsetZ>0.000</OffsetZ>
        <Heading>178.0</Heading>
    </FED>
    <FED Num="129">
        <FeatureCtIdx>2847</FeatureCtIdx>
        <OffsetX>-1186.792</OffsetX>
        <OffsetY>-4846.755</OffsetY>
        <OffsetZ>0.000</OffsetZ>
        <Heading>178.0</Heading>
    </FED>
    <FED Num="130">
        <FeatureCtIdx>2847</FeatureCtIdx>
        <OffsetX>-743.962</OffsetX>
        <OffsetY>-5025.472</OffsetY>
        <OffsetZ>0.000</OffsetZ>
        <Heading>178.0</Heading>
    </FED>
    <FED Num="131">
        <FeatureCtIdx>2847</FeatureCtIdx>
        <OffsetX>-848.962</OffsetX>
        <OffsetY>-5028.909</OffsetY>
        <OffsetZ>0.000</OffsetZ>
        <Heading>178.0</Heading>
    </FED>
    <FED Num="132">
        <FeatureCtIdx>2847</FeatureCtIdx>
        <OffsetX>-952.398</OffsetX>
        <OffsetY>-5032.347</OffsetY>
        <OffsetZ>0.000</OffsetZ>
        <Heading>178.0</Heading>
    </FED>
    <FED Num="133">
        <FeatureCtIdx>2847</FeatureCtIdx>
        <OffsetX>-1056.462</OffsetX>
        <OffsetY>-5036.409</OffsetY>
        <OffsetZ>0.000</OffsetZ>
        <Heading>178.0</Heading>
    </FED>
    <FED Num="134">
        <FeatureCtIdx>2847</FeatureCtIdx>
        <OffsetX>-1160.837</OffsetX>
        <OffsetY>-5038.284</OffsetY>
        <OffsetZ>0.000</OffsetZ>
        <Heading>178.0</Heading>
    </FED>
    <FED Num="135">
        <FeatureCtIdx>2847</FeatureCtIdx>
        <OffsetX>-740.233</OffsetX>
        <OffsetY>-5224.938</OffsetY>
        <OffsetZ>0.000</OffsetZ>
        <Heading>178.0</Heading>
    </FED>
    <FED Num="136">
        <FeatureCtIdx>2847</FeatureCtIdx>
        <OffsetX>-845.233</OffsetX>
        <OffsetY>-5228.375</OffsetY>
        <OffsetZ>0.000</OffsetZ>
        <Heading>178.0</Heading>
    </FED>
    <FED Num="137">
        <FeatureCtIdx>2847</FeatureCtIdx>
        <OffsetX>-948.669</OffsetX>
        <OffsetY>-5231.813</OffsetY>
        <OffsetZ>0.000</OffsetZ>
        <Heading>178.0</Heading>
    </FED>
    <FED Num="138">
        <FeatureCtIdx>2847</FeatureCtIdx>
        <OffsetX>-1052.732</OffsetX>
        <OffsetY>-5235.875</OffsetY>
        <OffsetZ>0.000</OffsetZ>
        <Heading>178.0</Heading>
    </FED>
    <FED Num="139">
        <FeatureCtIdx>2847</FeatureCtIdx>
        <OffsetX>-1157.106</OffsetX>
        <OffsetY>-5237.750</OffsetY>
        <OffsetZ>0.000</OffsetZ>
        <Heading>178.0</Heading>
    </FED>
    <FED Num="140">
        <FeatureCtIdx>2847</FeatureCtIdx>
        <OffsetX>-1258.020</OffsetX>
        <OffsetY>-5631.896</OffsetY>
        <OffsetZ>0.000</OffsetZ>
        <Heading>176.0</Heading>
    </FED>
    <FED Num="141">
        <FeatureCtIdx>2847</FeatureCtIdx>
        <OffsetX>-426.491</OffsetX>
        <OffsetY>-5593.389</OffsetY>
        <OffsetZ>0.000</OffsetZ>
        <Heading>176.0</Heading>
    </FED>
    <FED Num="142">
        <FeatureCtIdx>2847</FeatureCtIdx>
        <OffsetX>-538.221</OffsetX>
        <OffsetY>-5593.619</OffsetY>
        <OffsetZ>0.000</OffsetZ>
        <Heading>176.0</Heading>
    </FED>
    <FED Num="143">
        <FeatureCtIdx>2847</FeatureCtIdx>
        <OffsetX>-658.343</OffsetX>
        <OffsetY>-5598.731</OffsetY>
        <OffsetZ>0.000</OffsetZ>
        <Heading>176.0</Heading>
    </FED>
    <FED Num="144">
        <FeatureCtIdx>2847</FeatureCtIdx>
        <OffsetX>-776.256</OffsetX>
        <OffsetY>-5606.144</OffsetY>
        <OffsetZ>0.000</OffsetZ>
        <Heading>176.0</Heading>
    </FED>
    <FED Num="145">
        <FeatureCtIdx>2847</FeatureCtIdx>
        <OffsetX>-898.998</OffsetX>
        <OffsetY>-5616.077</OffsetY>
        <OffsetZ>0.000</OffsetZ>
        <Heading>176.0</Heading>
    </FED>
    <FED Num="146">
        <FeatureCtIdx>2847</FeatureCtIdx>
        <OffsetX>-1007.176</OffsetX>
        <OffsetY>-5619.083</OffsetY>
        <OffsetZ>0.000</OffsetZ>
        <Heading>176.0</Heading>
    </FED>
    <FED Num="147">
        <FeatureCtIdx>2847</FeatureCtIdx>
        <OffsetX>-1130.384</OffsetX>
        <OffsetY>-5625.217</OffsetY>
        <OffsetZ>0.000</OffsetZ>
        <Heading>176.0</Heading>
    </FED>
    <FED Num="148">
        <FeatureCtIdx>2847</FeatureCtIdx>
        <OffsetX>-1337.455</OffsetX>
        <OffsetY>-5937.563</OffsetY>
        <OffsetZ>0.000</OffsetZ>
        <Heading>240.0</Heading>
    </FED>
    <FED Num="149">
        <FeatureCtIdx>2847</FeatureCtIdx>
        <OffsetX>-380.505</OffsetX>
        <OffsetY>-5812.430</OffsetY>
        <OffsetZ>0.000</OffsetZ>
        <Heading>176.0</Heading>
    </FED>
    <FED Num="150">
        <FeatureCtIdx>2847</FeatureCtIdx>
        <OffsetX>-509.667</OffsetX>
        <OffsetY>-5831.310</OffsetY>
        <OffsetZ>0.000</OffsetZ>
        <Heading>176.0</Heading>
    </FED>
    <FED Num="151">
        <FeatureCtIdx>2847</FeatureCtIdx>
        <OffsetX>-621.396</OffsetX>
        <OffsetY>-5831.540</OffsetY>
        <OffsetZ>0.000</OffsetZ>
        <Heading>176.0</Heading>
    </FED>
    <FED Num="152">
        <FeatureCtIdx>2847</FeatureCtIdx>
        <OffsetX>-741.519</OffsetX>
        <OffsetY>-5836.652</OffsetY>
        <OffsetZ>0.000</OffsetZ>
        <Heading>176.0</Heading>
    </FED>
    <FED Num="153">
        <FeatureCtIdx>2847</FeatureCtIdx>
        <OffsetX>-859.432</OffsetX>
        <OffsetY>-5844.064</OffsetY>
        <OffsetZ>0.000</OffsetZ>
        <Heading>176.0</Heading>
    </FED>
    <FED Num="154">
        <FeatureCtIdx>2847</FeatureCtIdx>
        <OffsetX>-982.175</OffsetX>
        <OffsetY>-5853.998</OffsetY>
        <OffsetZ>0.000</OffsetZ>
        <Heading>176.0</Heading>
    </FED>
    <FED Num="155">
        <FeatureCtIdx>2847</FeatureCtIdx>
        <OffsetX>-1090.350</OffsetX>
        <OffsetY>-5857.002</OffsetY>
        <OffsetZ>0.000</OffsetZ>
        <Heading>176.0</Heading>
    </FED>
    <FED Num="156">
        <FeatureCtIdx>2847</FeatureCtIdx>
        <OffsetX>-1151.108</OffsetX>
        <OffsetY>-6120.337</OffsetY>
        <OffsetZ>0.000</OffsetZ>
        <Heading>176.0</Heading>
    </FED>
    <FED Num="157">
        <FeatureCtIdx>2847</FeatureCtIdx>
        <OffsetX>-106.600</OffsetX>
        <OffsetY>-5828.547</OffsetY>
        <OffsetZ>0.000</OffsetZ>
        <Heading>76.0</Heading>
    </FED>
    <FED Num="158">
        <FeatureCtIdx>2847</FeatureCtIdx>
        <OffsetX>-174.739</OffsetX>
        <OffsetY>-6047.353</OffsetY>
        <OffsetZ>0.000</OffsetZ>
        <Heading>167.0</Heading>
    </FED>
    <FED Num="159">
        <FeatureCtIdx>2847</FeatureCtIdx>
        <OffsetX>-303.690</OffsetX>
        <OffsetY>-6055.628</OffsetY>
        <OffsetZ>0.000</OffsetZ>
        <Heading>176.0</Heading>
    </FED>
    <FED Num="160">
        <FeatureCtIdx>2847</FeatureCtIdx>
        <OffsetX>-424.128</OffsetX>
        <OffsetY>-6081.019</OffsetY>
        <OffsetZ>0.000</OffsetZ>
        <Heading>176.0</Heading>
    </FED>
    <FED Num="161">
        <FeatureCtIdx>2847</FeatureCtIdx>
        <OffsetX>-558.555</OffsetX>
        <OffsetY>-6084.013</OffsetY>
        <OffsetZ>0.000</OffsetZ>
        <Heading>176.0</Heading>
    </FED>
    <FED Num="162">
        <FeatureCtIdx>2847</FeatureCtIdx>
        <OffsetX>-672.225</OffsetX>
        <OffsetY>-6030.908</OffsetY>
        <OffsetZ>0.000</OffsetZ>
        <Heading>4.0</Heading>
    </FED>
    <FED Num="163">
        <FeatureCtIdx>2847</FeatureCtIdx>
        <OffsetX>-796.594</OffsetX>
        <OffsetY>-6096.538</OffsetY>
        <OffsetZ>0.000</OffsetZ>
        <Heading>176.0</Heading>
    </FED>
    <FED Num="164">
        <FeatureCtIdx>2847</FeatureCtIdx>
        <OffsetX>-919.334</OffsetX>
        <OffsetY>-6106.471</OffsetY>
        <OffsetZ>0.000</OffsetZ>
        <Heading>176.0</Heading>
    </FED>
    <FED Num="165">
        <FeatureCtIdx>2847</FeatureCtIdx>
        <OffsetX>-1027.512</OffsetX>
        <OffsetY>-6109.475</OffsetY>
        <OffsetZ>0.000</OffsetZ>
        <Heading>176.0</Heading>
    </FED>
    <FED Num="166">
        <FeatureCtIdx>2847</FeatureCtIdx>
        <OffsetX>-1433.956</OffsetX>
        <OffsetY>-5770.747</OffsetY>
        <OffsetZ>0.000</OffsetZ>
        <Heading>216.0</Heading>
    </FED>
    <FED Num="167">
        <FeatureCtIdx>2847</FeatureCtIdx>
        <OffsetX>-1623.974</OffsetX>
        <OffsetY>-5595.664</OffsetY>
        <OffsetZ>0.000</OffsetZ>
        <Heading>216.0</Heading>
    </FED>
    <FED Num="168">
        <FeatureCtIdx>2847</FeatureCtIdx>
        <OffsetX>-1813.993</OffsetX>
        <OffsetY>-5420.582</OffsetY>
        <OffsetZ>0.000</OffsetZ>
        <Heading>216.0</Heading>
    </FED>
    <FED Num="169">
        <FeatureCtIdx>2847</FeatureCtIdx>
        <OffsetX>-2004.011</OffsetX>
        <OffsetY>-5245.498</OffsetY>
        <OffsetZ>0.000</OffsetZ>
        <Heading>216.0</Heading>
    </FED>
    <FED Num="170">
        <FeatureCtIdx>2847</FeatureCtIdx>
        <OffsetX>-2191.481</OffsetX>
        <OffsetY>-4660.513</OffsetY>
        <OffsetZ>0.000</OffsetZ>
        <Heading>120.0</Heading>
    </FED>
    <FED Num="171">
        <FeatureCtIdx>2847</FeatureCtIdx>
        <OffsetX>-2390.336</OffsetX>
        <OffsetY>-4477.498</OffsetY>
        <OffsetZ>0.000</OffsetZ>
        <Heading>310.0</Heading>
    </FED>
    <FED Num="172">
        <FeatureCtIdx>2847</FeatureCtIdx>
        <OffsetX>-2393.621</OffsetX>
        <OffsetY>-5027.008</OffsetY>
        <OffsetZ>0.000</OffsetZ>
        <Heading>310.0</Heading>
    </FED>
    <FED Num="173">
        <FeatureCtIdx>2847</FeatureCtIdx>
        <OffsetX>-2694.581</OffsetX>
        <OffsetY>-4771.648</OffsetY>
        <OffsetZ>0.000</OffsetZ>
        <Heading>20.0</Heading>
    </FED>
    <FED Num="174">
        <FeatureCtIdx>2847</FeatureCtIdx>
        <OffsetX>-3045.416</OffsetX>
        <OffsetY>-4448.458</OffsetY>
        <OffsetZ>0.000</OffsetZ>
        <Heading>20.0</Heading>
    </FED>
    <FED Num="175">
        <FeatureCtIdx>2633</FeatureCtIdx>
        <OffsetX>-2725.924</OffsetX>
        <OffsetY>-3880.964</OffsetY>
        <OffsetZ>0.000</OffsetZ>
        <Heading>359.0</Heading>
    </FED>
    <FED Num="176">
        <FeatureCtIdx>2629</FeatureCtIdx>
        <OffsetX>-2390.975</OffsetX>
        <OffsetY>-3871.750</OffsetY>
        <OffsetZ>0.000</OffsetZ>
        <Heading>359.0</Heading>
    </FED>
    <FED Num="177">
        <FeatureCtIdx>2630</FeatureCtIdx>
        <OffsetX>-1988.054</OffsetX>
        <OffsetY>-3873.853</OffsetY>
        <OffsetZ>0.000</OffsetZ>
        <Heading>359.0</Heading>
    </FED>
    <FED Num="178">
        <FeatureCtIdx>2633</FeatureCtIdx>
        <OffsetX>-1737.700</OffsetX>
        <OffsetY>-3864.052</OffsetY>
        <OffsetZ>0.000</OffsetZ>
        <Heading>0.0</Heading>
    </FED>
    <FED Num="179">
        <FeatureCtIdx>2634</FeatureCtIdx>
        <OffsetX>-2379.051</OffsetX>
        <OffsetY>-4240.696</OffsetY>
        <OffsetZ>0.000</OffsetZ>
        <Heading>269.0</Heading>
    </FED>
    <FED Num="180">
        <FeatureCtIdx>2656</FeatureCtIdx>
        <OffsetX>-1143.313</OffsetX>
        <OffsetY>-4432.344</OffsetY>
        <OffsetZ>0.000</OffsetZ>
        <Heading>358.0</Heading>
    </FED>
    <FED Num="181">
        <FeatureCtIdx>1019</FeatureCtIdx>
        <Value>60</Value>
        <OffsetX>-1659.000</OffsetX>
        <OffsetY>-4564.000</OffsetY>
        <OffsetZ>0.000</OffsetZ>
        <Heading>89.0</Heading>
    </FED>
    <FED Num="182">
        <FeatureCtIdx>1019</FeatureCtIdx>
        <Value>60</Value>
        <OffsetX>-1652.000</OffsetX>
        <OffsetY>-4910.000</OffsetY>
        <OffsetZ>0.000</OffsetZ>
        <Heading>89.0</Heading>
    </FED>
    <FED Num="183">
        <FeatureCtIdx>2586</FeatureCtIdx>
        <Value>60</Value>
        <OffsetX>-1642.819</OffsetX>
        <OffsetY>-5034.281</OffsetY>
        <OffsetZ>0.000</OffsetZ>
        <Heading>269.0</Heading>
    </FED>
    <FED Num="184">
        <FeatureCtIdx>2586</FeatureCtIdx>
        <Value>60</Value>
        <OffsetX>-1643.204</OffsetX>
        <OffsetY>-5163.809</OffsetY>
        <OffsetZ>0.000</OffsetZ>
        <Heading>269.0</Heading>
    </FED>
    <FED Num="185">
        <FeatureCtIdx>2586</FeatureCtIdx>
        <Value>60</Value>
        <OffsetX>-1643.589</OffsetX>
        <OffsetY>-5293.336</OffsetY>
        <OffsetZ>0.000</OffsetZ>
        <Heading>269.0</Heading>
    </FED>
    <FED Num="186">
        <FeatureCtIdx>2586</FeatureCtIdx>
        <Value>60</Value>
        <OffsetX>-1460.000</OffsetX>
        <OffsetY>-5303.000</OffsetY>
        <OffsetZ>0.000</OffsetZ>
        <Heading>274.0</Heading>
    </FED>
    <FED Num="187">
        <FeatureCtIdx>2586</FeatureCtIdx>
        <Value>60</Value>
        <OffsetX>-1433.000</OffsetX>
        <OffsetY>-5110.000</OffsetY>
        <OffsetZ>0.000</OffsetZ>
        <Heading>268.0</Heading>
    </FED>
    <FED Num="188">
        <FeatureCtIdx>2586</FeatureCtIdx>
        <Value>60</Value>
        <OffsetX>-1455.000</OffsetX>
        <OffsetY>-4949.000</OffsetY>
        <OffsetZ>0.000</OffsetZ>
        <Heading>359.0</Heading>
    </FED>
    <FED Num="189">
        <FeatureCtIdx>2633</FeatureCtIdx>
        <OffsetX>-1412.596</OffsetX>
        <OffsetY>-3912.088</OffsetY>
        <OffsetZ>0.000</OffsetZ>
        <Heading>90.0</Heading>
    </FED>
    <FED Num="190">
        <FeatureCtIdx>2634</FeatureCtIdx>
        <OffsetX>-1587.429</OffsetX>
        <OffsetY>-4222.746</OffsetY>
        <OffsetZ>0.000</OffsetZ>
        <Heading>90.0</Heading>
    </FED>
    <FED Num="191">
        <FeatureCtIdx>2634</FeatureCtIdx>
        <OffsetX>-1848.397</OffsetX>
        <OffsetY>-4228.972</OffsetY>
        <OffsetZ>0.000</OffsetZ>
        <Heading>90.0</Heading>
    </FED>
    <FED Num="192">
        <FeatureCtIdx>2634</FeatureCtIdx>
        <OffsetX>-2110.608</OffsetX>
        <OffsetY>-4240.921</OffsetY>
        <OffsetZ>0.000</OffsetZ>
        <Heading>90.0</Heading>
    </FED>
    <FED Num="193">
        <FeatureCtIdx>2657</FeatureCtIdx>
        <OffsetX>-946.669</OffsetX>
        <OffsetY>-5293.482</OffsetY>
        <OffsetZ>0.000</OffsetZ>
        <Heading>178.0</Heading>
    </FED>
    <FED Num="194">
        <FeatureCtIdx>2657</FeatureCtIdx>
        <OffsetX>-950.717</OffsetX>
        <OffsetY>-5093.056</OffsetY>
        <OffsetZ>0.000</OffsetZ>
        <Heading>178.0</Heading>
    </FED>
    <FED Num="195">
        <FeatureCtIdx>2657</FeatureCtIdx>
        <OffsetX>-976.232</OffsetX>
        <OffsetY>-4902.532</OffsetY>
        <OffsetZ>0.000</OffsetZ>
        <Heading>178.0</Heading>
    </FED>
    <FED Num="196">
        <FeatureCtIdx>2657</FeatureCtIdx>
        <OffsetX>-978.862</OffsetX>
        <OffsetY>-4741.483</OffsetY>
        <OffsetZ>0.000</OffsetZ>
        <Heading>178.0</Heading>
    </FED>
    <FED Num="197">
        <FeatureCtIdx>2657</FeatureCtIdx>
        <OffsetX>-988.710</OffsetX>
        <OffsetY>-4581.793</OffsetY>
        <OffsetZ>0.000</OffsetZ>
        <Heading>178.0</Heading>
    </FED>
    <FED Num="198">
        <FeatureCtIdx>2655</FeatureCtIdx>
        <OffsetX>-2634.434</OffsetX>
        <OffsetY>-4244.570</OffsetY>
        <OffsetZ>0.000</OffsetZ>
        <Heading>269.0</Heading>
    </FED>
    <FED Num="199">
        <FeatureCtIdx>869</FeatureCtIdx>
        <OffsetX>-2079.927</OffsetX>
        <OffsetY>-4857.521</OffsetY>
        <OffsetZ>0.000</OffsetZ>
        <Heading>179.0</Heading>
    </FED>
    <FED Num="200">
        <FeatureCtIdx>886</FeatureCtIdx>
        <Value>5</Value>
        <OffsetX>-2371.469</OffsetX>
        <OffsetY>-4656.286</OffsetY>
        <OffsetZ>0.000</OffsetZ>
        <Heading>37.0</Heading>
    </FED>
    <FED Num="201">
        <FeatureCtIdx>1014</FeatureCtIdx>
        <Value>10</Value>
        <OffsetX>-2701.609</OffsetX>
        <OffsetY>-4578.951</OffsetY>
        <OffsetZ>0.000</OffsetZ>
        <Heading>310.0</Heading>
    </FED>
    <FED Num="202">
        <FeatureCtIdx>1325</FeatureCtIdx>
        <Value>10</Value>
        <OffsetX>-1900.649</OffsetX>
        <OffsetY>-5407.490</OffsetY>
        <OffsetZ>0.000</OffsetZ>
        <Heading>222.0</Heading>
    </FED>
    <FED Num="203">
        <FeatureCtIdx>1387</FeatureCtIdx>
        <Value>20</Value>
        <OffsetX>-2969.699</OffsetX>
        <OffsetY>-4724.702</OffsetY>
        <OffsetZ>0.000</OffsetZ>
        <Heading>43.0</Heading>
    </FED>
    <FED Num="204">
        <FeatureCtIdx>2659</FeatureCtIdx>
        <OffsetX>-2401.231</OffsetX>
        <OffsetY>-4975.016</OffsetY>
        <OffsetZ>0.000</OffsetZ>
        <Heading>129.0</Heading>
    </FED>
    <FED Num="205">
        <FeatureCtIdx>2659</FeatureCtIdx>
        <OffsetX>-2299.380</OffsetX>
        <OffsetY>-4843.766</OffsetY>
        <OffsetZ>0.000</OffsetZ>
        <Heading>129.0</Heading>
    </FED>
    <FED Num="206">
        <FeatureCtIdx>2496</FeatureCtIdx>
        <OffsetX>-1762.168</OffsetX>
        <OffsetY>-4523.772</OffsetY>
        <OffsetZ>0.000</OffsetZ>
        <Heading>179.0</Heading>
    </FED>
    <FED Num="207">
        <FeatureCtIdx>2496</FeatureCtIdx>
        <OffsetX>-1546.918</OffsetX>
        <OffsetY>-4522.722</OffsetY>
        <OffsetZ>0.000</OffsetZ>
        <Heading>179.0</Heading>
    </FED>
    <FED Num="208">
        <FeatureCtIdx>2499</FeatureCtIdx>
        <OffsetX>-1746.620</OffsetX>
        <OffsetY>-5103.052</OffsetY>
        <OffsetZ>0.000</OffsetZ>
        <Heading>89.0</Heading>
    </FED>
    <FED Num="209">
        <FeatureCtIdx>2499</FeatureCtIdx>
        <OffsetX>-1532.870</OffsetX>
        <OffsetY>-5105.902</OffsetY>
        <OffsetZ>0.000</OffsetZ>
        <Heading>89.0</Heading>
    </FED>
    <FED Num="210">
        <FeatureCtIdx>869</FeatureCtIdx>
        <OffsetX>-2333.095</OffsetX>
        <OffsetY>-2712.892</OffsetY>
        <OffsetZ>0.000</OffsetZ>
        <Heading>242.0</Heading>
    </FED>
    <FED Num="211">
        <FeatureCtIdx>2911</FeatureCtIdx>
        <OffsetX>-2212.859</OffsetX>
        <OffsetY>-5053.860</OffsetY>
        <OffsetZ>0.000</OffsetZ>
        <Heading>1.0</Heading>
    </FED>
    <FED Num="212">
        <FeatureCtIdx>869</FeatureCtIdx>
        <OffsetX>-2927.127</OffsetX>
        <OffsetY>-2638.721</OffsetY>
        <OffsetZ>0.000</OffsetZ>
        <Heading>154.0</Heading>
    </FED>
    <FED Num="213">
        <FeatureCtIdx>589</FeatureCtIdx>
        <OffsetX>-2862.750</OffsetX>
        <OffsetY>-8417.250</OffsetY>
        <OffsetZ>0.000</OffsetZ>
        <Heading>357.0</Heading>
    </FED>
    <FED Num="214">
        <FeatureCtIdx>589</FeatureCtIdx>
        <OffsetX>-2867.400</OffsetX>
        <OffsetY>-8324.851</OffsetY>
        <OffsetZ>0.000</OffsetZ>
        <Heading>357.0</Heading>
    </FED>
    <FED Num="215">
        <FeatureCtIdx>2911</FeatureCtIdx>
        <OffsetX>-3690.552</OffsetX>
        <OffsetY>-4697.059</OffsetY>
        <OffsetZ>0.000</OffsetZ>
        <Heading>176.0</Heading>
    </FED>
    <FED Num="216">
        <FeatureCtIdx>2911</FeatureCtIdx>
        <OffsetX>-3692.653</OffsetX>
        <OffsetY>-4655.435</OffsetY>
        <OffsetZ>0.000</OffsetZ>
        <Heading>176.0</Heading>
    </FED>
    <FED Num="217">
        <FeatureCtIdx>2911</FeatureCtIdx>
        <OffsetX>-3694.752</OffsetX>
        <OffsetY>-4613.810</OffsetY>
        <OffsetZ>0.000</OffsetZ>
        <Heading>176.0</Heading>
    </FED>
    <FED Num="218">
        <FeatureCtIdx>2659</FeatureCtIdx>
        <OffsetX>-2953.073</OffsetX>
        <OffsetY>-4190.534</OffsetY>
        <OffsetZ>0.000</OffsetZ>
        <Heading>357.0</Heading>
    </FED>
    <FED Num="219">
        <FeatureCtIdx>2659</FeatureCtIdx>
        <OffsetX>-2990.708</OffsetX>
        <OffsetY>-4237.589</OffsetY>
        <OffsetZ>0.000</OffsetZ>
        <Heading>267.0</Heading>
    </FED>
    <FED Num="220">
        <FeatureCtIdx>2659</FeatureCtIdx>
        <OffsetX>-3017.760</OffsetX>
        <OffsetY>-3903.104</OffsetY>
        <OffsetZ>0.000</OffsetZ>
        <Heading>267.0</Heading>
    </FED>
    <FED Num="221">
        <FeatureCtIdx>2659</FeatureCtIdx>
        <OffsetX>-3102.635</OffsetX>
        <OffsetY>-3907.515</OffsetY>
        <OffsetZ>0.000</OffsetZ>
        <Heading>267.0</Heading>
    </FED>
    <FED Num="222">
        <FeatureCtIdx>2659</FeatureCtIdx>
        <OffsetX>-3178.553</OffsetX>
        <OffsetY>-4001.203</OffsetY>
        <OffsetZ>0.000</OffsetZ>
        <Heading>359.0</Heading>
    </FED>
    <FED Num="223">
        <FeatureCtIdx>2659</FeatureCtIdx>
        <OffsetX>-3177.020</OffsetX>
        <OffsetY>-4086.166</OffsetY>
        <OffsetZ>0.000</OffsetZ>
        <Heading>359.0</Heading>
    </FED>
    <FED Num="224">
        <FeatureCtIdx>2659</FeatureCtIdx>
        <OffsetX>-3175.594</OffsetX>
        <OffsetY>-4171.207</OffsetY>
        <OffsetZ>0.000</OffsetZ>
        <Heading>359.0</Heading>
    </FED>
    <FED Num="225">
        <FeatureCtIdx>152</FeatureCtIdx>
        <Value>50</Value>
        <OffsetX>-3074.958</OffsetX>
        <OffsetY>-3995.292</OffsetY>
        <OffsetZ>0.000</OffsetZ>
        <Heading>357.0</Heading>
    </FED>
    <FED Num="226">
        <FeatureCtIdx>152</FeatureCtIdx>
        <Value>50</Value>
        <OffsetX>-3070.428</OffsetX>
        <OffsetY>-4079.892</OffsetY>
        <OffsetZ>0.000</OffsetZ>
        <Heading>357.0</Heading>
    </FED>
    <FED Num="227">
        <FeatureCtIdx>152</FeatureCtIdx>
        <OffsetX>-2349.828</OffsetX>
        <OffsetY>-4910.592</OffsetY>
        <OffsetZ>0.000</OffsetZ>
        <Heading>39.0</Heading>
    </FED>
    <FED Num="228">
        <FeatureCtIdx>2585</FeatureCtIdx>
        <Value>60</Value>
        <OffsetX>-3176.000</OffsetX>
        <OffsetY>-2565.000</OffsetY>
        <OffsetZ>0.000</OffsetZ>
        <Heading>89.0</Heading>
    </FED>
    <FED Num="229">
        <FeatureCtIdx>2585</FeatureCtIdx>
        <Value>60</Value>
        <OffsetX>-3195.000</OffsetX>
        <OffsetY>-3077.000</OffsetY>
        <OffsetZ>0.000</OffsetZ>
        <Heading>358.0</Heading>
    </FED>
    <FED Num="230">
        <FeatureCtIdx>1318</FeatureCtIdx>
        <Value>45</Value>
        <OffsetX>-3730.000</OffsetX>
        <OffsetY>-4171.000</OffsetY>
        <OffsetZ>0.000</OffsetZ>
        <Heading>356.0</Heading>
    </FED>
    <FED Num="231">
        <FeatureCtIdx>886</FeatureCtIdx>
        <Value>5</Value>
        <OffsetX>-3300.938</OffsetX>
        <OffsetY>-4602.953</OffsetY>
        <OffsetZ>0.000</OffsetZ>
        <Heading>356.0</Heading>
    </FED>
    <FED Num="232">
        <FeatureCtIdx>886</FeatureCtIdx>
        <Value>5</Value>
        <OffsetX>-3419.648</OffsetX>
        <OffsetY>-4422.675</OffsetY>
        <OffsetZ>0.000</OffsetZ>
        <Heading>356.0</Heading>
    </FED>
    <FED Num="233">
        <FeatureCtIdx>886</FeatureCtIdx>
        <Value>5</Value>
        <OffsetX>-3595.448</OffsetX>
        <OffsetY>-4292.175</OffsetY>
        <OffsetZ>0.000</OffsetZ>
        <Heading>356.0</Heading>
    </FED>
    <FED Num="234">
        <FeatureCtIdx>886</FeatureCtIdx>
        <Value>5</Value>
        <OffsetX>-3328.748</OffsetX>
        <OffsetY>-4272.225</OffsetY>
        <OffsetZ>0.000</OffsetZ>
        <Heading>356.0</Heading>
    </FED>
    <FED Num="235">
        <FeatureCtIdx>888</FeatureCtIdx>
        <OffsetX>-3435.034</OffsetX>
        <OffsetY>-4096.890</OffsetY>
        <OffsetZ>0.000</OffsetZ>
        <Heading>179.0</Heading>
    </FED>
    <FED Num="236">
        <FeatureCtIdx>888</FeatureCtIdx>
        <OffsetX>-3621.335</OffsetX>
        <OffsetY>-4107.011</OffsetY>
        <OffsetZ>0.000</OffsetZ>
        <Heading>179.0</Heading>
    </FED>
    <FED Num="237">
        <FeatureCtIdx>888</FeatureCtIdx>
        <OffsetX>-3687.004</OffsetX>
        <OffsetY>-3957.211</OffsetY>
        <OffsetZ>0.000</OffsetZ>
        <Heading>179.0</Heading>
    </FED>
    <FED Num="238">
        <FeatureCtIdx>888</FeatureCtIdx>
        <OffsetX>-3609.722</OffsetX>
        <OffsetY>-4476.614</OffsetY>
        <OffsetZ>0.000</OffsetZ>
        <Heading>269.0</Heading>
    </FED>
    <FED Num="239">
        <FeatureCtIdx>1318</FeatureCtIdx>
        <Value>45</Value>
        <OffsetX>-3318.515</OffsetX>
        <OffsetY>-4019.086</OffsetY>
        <OffsetZ>0.000</OffsetZ>
        <Heading>89.0</Heading>
    </FED>
    <FED Num="240">
        <FeatureCtIdx>2385</FeatureCtIdx>
        <OffsetX>-2980.740</OffsetX>
        <OffsetY>-5657.300</OffsetY>
        <OffsetZ>0.000</OffsetZ>
        <Heading>216.0</Heading>
    </FED>
    <FED Num="241">
        <FeatureCtIdx>2385</FeatureCtIdx>
        <OffsetX>-2815.318</OffsetX>
        <OffsetY>-5611.191</OffsetY>
        <OffsetZ>0.000</OffsetZ>
        <Heading>275.0</Heading>
    </FED>
    <FED Num="242">
        <FeatureCtIdx>2498</FeatureCtIdx>
        <OffsetX>-2911.163</OffsetX>
        <OffsetY>-5836.096</OffsetY>
        <OffsetZ>0.000</OffsetZ>
        <Heading>278.0</Heading>
    </FED>
    <FED Num="243">
        <FeatureCtIdx>2498</FeatureCtIdx>
        <OffsetX>-2897.018</OffsetX>
        <OffsetY>-5737.351</OffsetY>
        <OffsetZ>0.000</OffsetZ>
        <Heading>278.0</Heading>
    </FED>
    <FED Num="244">
        <FeatureCtIdx>2498</FeatureCtIdx>
        <OffsetX>-2806.027</OffsetX>
        <OffsetY>-5750.232</OffsetY>
        <OffsetZ>0.000</OffsetZ>
        <Heading>98.0</Heading>
    </FED>
    <FED Num="245">
        <FeatureCtIdx>1102</FeatureCtIdx>
        <OffsetX>-2800.945</OffsetX>
        <OffsetY>-5762.333</OffsetY>
        <OffsetZ>0.000</OffsetZ>
        <Heading>8.0</Heading>
    </FED>
    <FED Num="246">
        <FeatureCtIdx>1101</FeatureCtIdx>
        <OffsetX>-2888.177</OffsetX>
        <OffsetY>-5839.656</OffsetY>
        <OffsetZ>0.000</OffsetZ>
        <Heading>188.0</Heading>
    </FED>
    <FED Num="247">
        <FeatureCtIdx>1103</FeatureCtIdx>
        <OffsetX>-3001.416</OffsetX>
        <OffsetY>-5951.864</OffsetY>
        <OffsetZ>0.000</OffsetZ>
        <Heading>268.0</Heading>
    </FED>
    <FED Num="248">
        <FeatureCtIdx>2705</FeatureCtIdx>
        <OffsetX>-5395.548</OffsetX>
        <OffsetY>-4043.149</OffsetY>
        <OffsetZ>0.000</OffsetZ>
        <Heading>178.0</Heading>
    </FED>
    <FED Num="249">
        <FeatureCtIdx>2705</FeatureCtIdx>
        <OffsetX>-5352.648</OffsetX>
        <OffsetY>-4035.649</OffsetY>
        <OffsetZ>0.000</OffsetZ>
        <Heading>178.0</Heading>
    </FED>
    <FED Num="250">
        <FeatureCtIdx>2728</FeatureCtIdx>
        <OffsetX>-5396.000</OffsetX>
        <OffsetY>-3982.000</OffsetY>
        <OffsetZ>0.000</OffsetZ>
        <Heading>358.0</Heading>
    </FED>
    <FED Num="251">
        <FeatureCtIdx>3533</FeatureCtIdx>
        <OffsetX>-3910.916</OffsetX>
        <OffsetY>-1903.469</OffsetY>
        <OffsetZ>-3.000</OffsetZ>
        <Heading>153.0</Heading>
    </FED>
    <FED Num="252">
        <FeatureCtIdx>3535</FeatureCtIdx>
        <OffsetX>-3914.938</OffsetX>
        <OffsetY>-1893.625</OffsetY>
        <OffsetZ>-3.000</OffsetZ>
        <Heading>153.0</Heading>
    </FED>
    <FED Num="253">
        <FeatureCtIdx>875</FeatureCtIdx>
        <OffsetX>-3912.859</OffsetX>
        <OffsetY>-1899.685</OffsetY>
        <OffsetZ>0.000</OffsetZ>
        <Heading>153.0</Heading>
    </FED>
</FEDRecords>
